Workbook

Sheet Legenda
A1: SERVIZI ECOLOGICI S.R.L. – Gestione contatti, servizi e obblighi di legge
A2: Creato il 25/09/2026 – fonti: area clienti Italiaonline/PgCasa, sito serviziecologici.it, normativa vigente
A4: Foglio | B4: A cosa serve | C4: Cosa compilare
A5: Servizi e obblighi | B5: Tutti i servizi dell'azienda con autorizzazioni, documenti, sicurezza, trasporto e scadenze di legge | C5: Colonna 'Verifica interna' (es. n. iscrizione Albo, scadenza)
A6: Iscrizione Albo | B6: Categorie, classi e scadenze dell'iscrizione MI03807 con stato automatico (VALIDA / RINNOVARE ORA) | C6: Aggiornare dopo ogni rinnovo
A7: Obblighi trasversali | B7: Obblighi che valgono per tutta l'azienda (Albo, RENTRI, MUD, DVR, privacy contatti…) | C7: Colonne 'Scadenza' e 'Responsabile'
A8: Registro | B8: Un rigo per ogni contatto (PgCasa, telefonate, moduli sito, Google…): esito PRESO / NON PRESO e motivo | C8: Tutte le celle gialle. Menù a tendina su Fonte, Tipo cliente, Area, Esito, Motivo
A9: Statistiche | B9: Conteggi automatici per servizio, zona, fonte, tipo cliente, esito e motivo; % lavori presi; costo per lavoro preso | C9: Niente: si aggiorna da solo
A10: Motivi | B10: Elenco dei motivi di lavoro non preso (usato dal menù a tendina) | C10: Aggiungere motivi in fondo se servono
A11: Pacchetti | B11: Pacchetti di servizi per tipo di cliente, con l'obbligo di legge che il pacchetto risolve | C11: Prezzo indicativo e note commerciali
A13: Colori | B13: Celle gialle = da compilare. Celle verdi = intestazioni di area. Il resto sono formule o testi di riferimento.
A14: Attenzione | B14: Le indicazioni normative sono una sintesi operativa, non un parere legale: verificare sempre con il consulente ambientale/RSPP e sul testo vigente delle norme.
A15: Registro chiamate | B15: Importate le 168 chiamate del file reg.chiamate.pdf (Reception, 2026) + 16 richieste PgCasa. Il registro originale NON ha l'esito: la colonna Esito è impostata a DA VERIFICARE, va aggiornata con PRESO / NON PRESO + Motivo.
A16: Ipotesi di lettura | B16: IT CANNE = ispezione TV canne fumarie; IT FOGNA = ispezione TV fognatura; PULIZ./PULIZIA, ANALISI e INSTALLAZI sono in area DA SPECIFICARE perché dal registro non si capisce quale servizio. Correggere dove serve.
A17: Dati Italiaonline (ultimi 6 mesi) | B17: 14.533 impression · 7.495 visualizzazioni · 2.859 visite · 500 chiamate · 331 indicazioni stradali · 157 clic sito · 37 moduli contatto · 17 preventivi · saldo PgCasa 62 €

Sheet Statistiche
A1: Statistiche contatti
A2: Si aggiornano da sole dal foglio Registro
A4: Totale contatti | B4: =COUNTA(Registro!$D$5:$D$804) -> 184
A5: Lavori PRESI | B5: =COUNTIF(Registro!$M$5:$M$804,"PRESO") -> 0
A6: NON PRESI | B6: =COUNTIF(Registro!$M$5:$M$804,"NON PRESO") -> 0
A7: Esito ancora da inserire | B7: =B4-B5-B6 -> 184
A8: % presi sui contatti chiusi | B8: =IFERROR(B5/(B5+B6),0) -> 0
A9: Contatti da Italiaonline (chiamate + PgCasa) | B9: =COUNTIF(Registro!$B$5:$B$804,"Italiaonline")+COUNTIF(Registro!$B$5:$B$804,"PgCasa (Italiaonline)") -> 56
A10: % contatti da Italiaonline | B10: =IFERROR(B9/B4,0) -> 0.30434783
A11: Costo contatti PgCasa € | B11: =SUM(Registro!$Q$5:$Q$804) -> 123
A12: Costo per lavoro preso € | B12: =IFERROR(B11/B5,0) -> 0
A13: Valore lavori fatti € | B13: =SUM(Registro!$P$5:$P$804) -> 0
A16: Per fonte del contatto (da dove ci conoscono)
A17: Fonte | B17: Contatti | C17: Presi | D17: Non presi | E17: Esito da inserire / in attesa | F17: % presi (sui chiusi) | G17: Costo contatti € | H17: Valore lavori €
A18: PgCasa (Italiaonline) | B18: =COUNTIF(Registro!$B$5:$B$804,$A18) -> 16 | C18: =COUNTIFS(Registro!$B$5:$B$804,$A18,Registro!$M$5:$M$804,"PRESO") -> 0 | D18: =COUNTIFS(Registro!$B$5:$B$804,$A18,Registro!$M$5:$M$804,"NON PRESO") -> 0 | E18: =B18-C18-D18 -> 16 | F18: =IFERROR(C18/(C18+D18),0) -> 0 | G18: =SUMIF(Registro!$B$5:$B$804,$A18,Registro!$Q$5:$Q$804) -> 123 | H18: =SUMIFS(Registro!$P$5:$P$804,Registro!$B$5:$B$804,$A18,Registro!$M$5:$M$804,"PRESO") -> 0
A19: Italiaonline | B19: =COUNTIF(Registro!$B$5:$B$804,$A19) -> 40 | C19: =COUNTIFS(Registro!$B$5:$B$804,$A19,Registro!$M$5:$M$804,"PRESO") -> 0 | D19: =COUNTIFS(Registro!$B$5:$B$804,$A19,Registro!$M$5:$M$804,"NON PRESO") -> 0 | E19: =B19-C19-D19 -> 40 | F19: =IFERROR(C19/(C19+D19),0) -> 0 | G19: =SUMIF(Registro!$B$5:$B$804,$A19,Registro!$Q$5:$Q$804) -> 0 | H19: =SUMIFS(Registro!$P$5:$P$804,Registro!$B$5:$B$804,$A19,Registro!$M$5:$M$804,"PRESO") -> 0
A20: Internet | B20: =COUNTIF(Registro!$B$5:$B$804,$A20) -> 37 | C20: =COUNTIFS(Registro!$B$5:$B$804,$A20,Registro!$M$5:$M$804,"PRESO") -> 0 | D20: =COUNTIFS(Registro!$B$5:$B$804,$A20,Registro!$M$5:$M$804,"NON PRESO") -> 0 | E20: =B20-C20-D20 -> 37 | F20: =IFERROR(C20/(C20+D20),0) -> 0 | G20: =SUMIF(Registro!$B$5:$B$804,$A20,Registro!$Q$5:$Q$804) -> 0 | H20: =SUMIFS(Registro!$P$5:$P$804,Registro!$B$5:$B$804,$A20,Registro!$M$5:$M$804,"PRESO") -> 0
A21: Passaparola | B21: =COUNTIF(Registro!$B$5:$B$804,$A21) -> 83 | C21: =COUNTIFS(Registro!$B$5:$B$804,$A21,Registro!$M$5:$M$804,"PRESO") -> 0 | D21: =COUNTIFS(Registro!$B$5:$B$804,$A21,Registro!$M$5:$M$804,"NON PRESO") -> 0 | E21: =B21-C21-D21 -> 83 | F21: =IFERROR(C21/(C21+D21),0) -> 0 | G21: =SUMIF(Registro!$B$5:$B$804,$A21,Registro!$Q$5:$Q$804) -> 0 | H21: =SUMIFS(Registro!$P$5:$P$804,Registro!$B$5:$B$804,$A21,Registro!$M$5:$M$804,"PRESO") -> 0
A22: Pagine Gialle | B22: =COUNTIF(Registro!$B$5:$B$804,$A22) -> 1 | C22: =COUNTIFS(Registro!$B$5:$B$804,$A22,Registro!$M$5:$M$804,"PRESO") -> 0 | D22: =COUNTIFS(Registro!$B$5:$B$804,$A22,Registro!$M$5:$M$804,"NON PRESO") -> 0 | E22: =B22-C22-D22 -> 1 | F22: =IFERROR(C22/(C22+D22),0) -> 0 | G22: =SUMIF(Registro!$B$5:$B$804,$A22,Registro!$Q$5:$Q$804) -> 0 | H22: =SUMIFS(Registro!$P$5:$P$804,Registro!$B$5:$B$804,$A22,Registro!$M$5:$M$804,"PRESO") -> 0
A23: Quotidiani Online | B23: =COUNTIF(Registro!$B$5:$B$804,$A23) -> 2 | C23: =COUNTIFS(Registro!$B$5:$B$804,$A23,Registro!$M$5:$M$804,"PRESO") -> 0 | D23: =COUNTIFS(Registro!$B$5:$B$804,$A23,Registro!$M$5:$M$804,"NON PRESO") -> 0 | E23: =B23-C23-D23 -> 2 | F23: =IFERROR(C23/(C23+D23),0) -> 0 | G23: =SUMIF(Registro!$B$5:$B$804,$A23,Registro!$Q$5:$Q$804) -> 0 | H23: =SUMIFS(Registro!$P$5:$P$804,Registro!$B$5:$B$804,$A23,Registro!$M$5:$M$804,"PRESO") -> 0
A24: Pubblicità Automezzi | B24: =COUNTIF(Registro!$B$5:$B$804,$A24) -> 1 | C24: =COUNTIFS(Registro!$B$5:$B$804,$A24,Registro!$M$5:$M$804,"PRESO") -> 0 | D24: =COUNTIFS(Registro!$B$5:$B$804,$A24,Registro!$M$5:$M$804,"NON PRESO") -> 0 | E24: =B24-C24-D24 -> 1 | F24: =IFERROR(C24/(C24+D24),0) -> 0 | G24: =SUMIF(Registro!$B$5:$B$804,$A24,Registro!$Q$5:$Q$804) -> 0 | H24: =SUMIFS(Registro!$P$5:$P$804,Registro!$B$5:$B$804,$A24,Registro!$M$5:$M$804,"PRESO") -> 0
A25: Manifesti deratt. | B25: =COUNTIF(Registro!$B$5:$B$804,$A25) -> 1 | C25: =COUNTIFS(Registro!$B$5:$B$804,$A25,Registro!$M$5:$M$804,"PRESO") -> 0 | D25: =COUNTIFS(Registro!$B$5:$B$804,$A25,Registro!$M$5:$M$804,"NON PRESO") -> 0 | E25: =B25-C25-D25 -> 1 | F25: =IFERROR(C25/(C25+D25),0) -> 0 | G25: =SUMIF(Registro!$B$5:$B$804,$A25,Registro!$Q$5:$Q$804) -> 0 | H25: =SUMIFS(Registro!$P$5:$P$804,Registro!$B$5:$B$804,$A25,Registro!$M$5:$M$804,"PRESO") -> 0
A26: Imprese Ambiente | B26: =COUNTIF(Registro!$B$5:$B$804,$A26) -> 1 | C26: =COUNTIFS(Registro!$B$5:$B$804,$A26,Registro!$M$5:$M$804,"PRESO") -> 0 | D26: =COUNTIFS(Registro!$B$5:$B$804,$A26,Registro!$M$5:$M$804,"NON PRESO") -> 0 | E26: =B26-C26-D26 -> 1 | F26: =IFERROR(C26/(C26+D26),0) -> 0 | G26: =SUMIF(Registro!$B$5:$B$804,$A26,Registro!$Q$5:$Q$804) -> 0 | H26: =SUMIFS(Registro!$P$5:$P$804,Registro!$B$5:$B$804,$A26,Registro!$M$5:$M$804,"PRESO") -> 0
A27: Bus | B27: =COUNTIF(Registro!$B$5:$B$804,$A27) -> 1 | C27: =COUNTIFS(Registro!$B$5:$B$804,$A27,Registro!$M$5:$M$804,"PRESO") -> 0 | D27: =COUNTIFS(Registro!$B$5:$B$804,$A27,Registro!$M$5:$M$804,"NON PRESO") -> 0 | E27: =B27-C27-D27 -> 1 | F27: =IFERROR(C27/(C27+D27),0) -> 0 | G27: =SUMIF(Registro!$B$5:$B$804,$A27,Registro!$Q$5:$Q$804) -> 0 | H27: =SUMIFS(Registro!$P$5:$P$804,Registro!$B$5:$B$804,$A27,Registro!$M$5:$M$804,"PRESO") -> 0
A28: Altro | B28: =COUNTIF(Registro!$B$5:$B$804,$A28) -> 1 | C28: =COUNTIFS(Registro!$B$5:$B$804,$A28,Registro!$M$5:$M$804,"PRESO") -> 0 | D28: =COUNTIFS(Registro!$B$5:$B$804,$A28,Registro!$M$5:$M$804,"NON PRESO") -> 0 | E28: =B28-C28-D28 -> 1 | F28: =IFERROR(C28/(C28+D28),0) -> 0 | G28: =SUMIF(Registro!$B$5:$B$804,$A28,Registro!$Q$5:$Q$804) -> 0 | H28: =SUMIFS(Registro!$P$5:$P$804,Registro!$B$5:$B$804,$A28,Registro!$M$5:$M$804,"PRESO") -> 0
A29: TOTALE | B29: =SUM(B18:B28) -> 184 | C29: =SUM(C18:C28) -> 0 | D29: =SUM(D18:D28) -> 0 | E29: =SUM(E18:E28) -> 184 | F29: =IFERROR(C29/(C29+D29),0) -> 0 | G29: =SUM(G18:G28) -> 123 | H29: =SUM(H18:H28) -> 0
A31: Per area di servizio
A32: Area | B32: Contatti | C32: Presi | D32: Non presi | E32: Esito da inserire / in attesa | F32: % presi (sui chiusi) | G32: Costo contatti € | H32: Valore lavori €
A33: SPURGHI E RETI | B33: =COUNTIF(Registro!$J$5:$J$804,$A33) -> 30 | C33: =COUNTIFS(Registro!$J$5:$J$804,$A33,Registro!$M$5:$M$804,"PRESO") -> 0 | D33: =COUNTIFS(Registro!$J$5:$J$804,$A33,Registro!$M$5:$M$804,"NON PRESO") -> 0 | E33: =B33-C33-D33 -> 30 | F33: =IFERROR(C33/(C33+D33),0) -> 0 | G33: =SUMIF(Registro!$J$5:$J$804,$A33,Registro!$Q$5:$Q$804) -> 60 | H33: =SUMIFS(Registro!$P$5:$P$804,Registro!$J$5:$J$804,$A33,Registro!$M$5:$M$804,"PRESO") -> 0
A34: RIFIUTI | B34: =COUNTIF(Registro!$J$5:$J$804,$A34) -> 38 | C34: =COUNTIFS(Registro!$J$5:$J$804,$A34,Registro!$M$5:$M$804,"PRESO") -> 0 | D34: =COUNTIFS(Registro!$J$5:$J$804,$A34,Registro!$M$5:$M$804,"NON PRESO") -> 0 | E34: =B34-C34-D34 -> 38 | F34: =IFERROR(C34/(C34+D34),0) -> 0 | G34: =SUMIF(Registro!$J$5:$J$804,$A34,Registro!$Q$5:$Q$804) -> 0 | H34: =SUMIFS(Registro!$P$5:$P$804,Registro!$J$5:$J$804,$A34,Registro!$M$5:$M$804,"PRESO") -> 0
A35: BONIFICHE | B35: =COUNTIF(Registro!$J$5:$J$804,$A35) -> 38 | C35: =COUNTIFS(Registro!$J$5:$J$804,$A35,Registro!$M$5:$M$804,"PRESO") -> 0 | D35: =COUNTIFS(Registro!$J$5:$J$804,$A35,Registro!$M$5:$M$804,"NON PRESO") -> 0 | E35: =B35-C35-D35 -> 38 | F35: =IFERROR(C35/(C35+D35),0) -> 0 | G35: =SUMIF(Registro!$J$5:$J$804,$A35,Registro!$Q$5:$Q$804) -> 0 | H35: =SUMIFS(Registro!$P$5:$P$804,Registro!$J$5:$J$804,$A35,Registro!$M$5:$M$804,"PRESO") -> 0
A36: DISINFESTAZIONE | B36: =COUNTIF(Registro!$J$5:$J$804,$A36) -> 33 | C36: =COUNTIFS(Registro!$J$5:$J$804,$A36,Registro!$M$5:$M$804,"PRESO") -> 0 | D36: =COUNTIFS(Registro!$J$5:$J$804,$A36,Registro!$M$5:$M$804,"NON PRESO") -> 0 | E36: =B36-C36-D36 -> 33 | F36: =IFERROR(C36/(C36+D36),0) -> 0 | G36: =SUMIF(Registro!$J$5:$J$804,$A36,Registro!$Q$5:$Q$804) -> 63 | H36: =SUMIFS(Registro!$P$5:$P$804,Registro!$J$5:$J$804,$A36,Registro!$M$5:$M$804,"PRESO") -> 0
A37: IGIENE IMPIANTI | B37: =COUNTIF(Registro!$J$5:$J$804,$A37) -> 14 | C37: =COUNTIFS(Registro!$J$5:$J$804,$A37,Registro!$M$5:$M$804,"PRESO") -> 0 | D37: =COUNTIFS(Registro!$J$5:$J$804,$A37,Registro!$M$5:$M$804,"NON PRESO") -> 0 | E37: =B37-C37-D37 -> 14 | F37: =IFERROR(C37/(C37+D37),0) -> 0 | G37: =SUMIF(Registro!$J$5:$J$804,$A37,Registro!$Q$5:$Q$804) -> 0 | H37: =SUMIFS(Registro!$P$5:$P$804,Registro!$J$5:$J$804,$A37,Registro!$M$5:$M$804,"PRESO") -> 0
A38: NAUTICA | B38: =COUNTIF(Registro!$J$5:$J$804,$A38) -> 0 | C38: =COUNTIFS(Registro!$J$5:$J$804,$A38,Registro!$M$5:$M$804,"PRESO") -> 0 | D38: =COUNTIFS(Registro!$J$5:$J$804,$A38,Registro!$M$5:$M$804,"NON PRESO") -> 0 | E38: =B38-C38-D38 -> 0 | F38: =IFERROR(C38/(C38+D38),0) -> 0 | G38: =SUMIF(Registro!$J$5:$J$804,$A38,Registro!$Q$5:$Q$804) -> 0 | H38: =SUMIFS(Registro!$P$5:$P$804,Registro!$J$5:$J$804,$A38,Registro!$M$5:$M$804,"PRESO") -> 0
A39: CONSULENZA | B39: =COUNTIF(Registro!$J$5:$J$804,$A39) -> 0 | C39: =COUNTIFS(Registro!$J$5:$J$804,$A39,Registro!$M$5:$M$804,"PRESO") -> 0 | D39: =COUNTIFS(Registro!$J$5:$J$804,$A39,Registro!$M$5:$M$804,"NON PRESO") -> 0 | E39: =B39-C39-D39 -> 0 | F39: =IFERROR(C39/(C39+D39),0) -> 0 | G39: =SUMIF(Registro!$J$5:$J$804,$A39,Registro!$Q$5:$Q$804) -> 0 | H39: =SUMIFS(Registro!$P$5:$P$804,Registro!$J$5:$J$804,$A39,Registro!$M$5:$M$804,"PRESO") -> 0
A40: DA SPECIFICARE | B40: =COUNTIF(Registro!$J$5:$J$804,$A40) -> 31 | C40: =COUNTIFS(Registro!$J$5:$J$804,$A40,Registro!$M$5:$M$804,"PRESO") -> 0 | D40: =COUNTIFS(Registro!$J$5:$J$804,$A40,Registro!$M$5:$M$804,"NON PRESO") -> 0 | E40: =B40-C40-D40 -> 31 | F40: =IFERROR(C40/(C40+D40),0) -> 0 | G40: =SUMIF(Registro!$J$5:$J$804,$A40,Registro!$Q$5:$Q$804) -> 0 | H40: =SUMIFS(Registro!$P$5:$P$804,Registro!$J$5:$J$804,$A40,Registro!$M$5:$M$804,"PRESO") -> 0
A41: TOTALE | B41: =SUM(B33:B40) -> 184 | C41: =SUM(C33:C40) -> 0 | D41: =SUM(D33:D40) -> 0 | E41: =SUM(E33:E40) -> 184 | F41: =IFERROR(C41/(C41+D41),0) -> 0 | G41: =SUM(G33:G40) -> 123 | H41: =SUM(H33:H40) -> 0
A43: Per servizio
A44: Servizio | B44: Contatti | C44: Presi | D44: Non presi | E44: Esito da inserire / in attesa | F44: % presi (sui chiusi) | G44: Costo contatti € | H44: Valore lavori €
A45: Canaljet – autospurgo fosse biologiche, fognature, pozzetti, degrassatori | B45: =COUNTIF(Registro!$K$5:$K$804,$A45) -> 19 | C45: =COUNTIFS(Registro!$K$5:$K$804,$A45,Registro!$M$5:$M$804,"PRESO") -> 0 | D45: =COUNTIFS(Registro!$K$5:$K$804,$A45,Registro!$M$5:$M$804,"NON PRESO") -> 0 | E45: =B45-C45-D45 -> 19 | F45: =IFERROR(C45/(C45+D45),0) -> 0 | G45: =SUMIF(Registro!$K$5:$K$804,$A45,Registro!$Q$5:$Q$804) -> 60 | H45: =SUMIFS(Registro!$P$5:$P$804,Registro!$K$5:$K$804,$A45,Registro!$M$5:$M$804,"PRESO") -> 0
A46: Ispezioni televisive e mappature reti | B46: =COUNTIF(Registro!$K$5:$K$804,$A46) -> 4 | C46: =COUNTIFS(Registro!$K$5:$K$804,$A46,Registro!$M$5:$M$804,"PRESO") -> 0 | D46: =COUNTIFS(Registro!$K$5:$K$804,$A46,Registro!$M$5:$M$804,"NON PRESO") -> 0 | E46: =B46-C46-D46 -> 4 | F46: =IFERROR(C46/(C46+D46),0) -> 0 | G46: =SUMIF(Registro!$K$5:$K$804,$A46,Registro!$Q$5:$Q$804) -> 0 | H46: =SUMIFS(Registro!$P$5:$P$804,Registro!$K$5:$K$804,$A46,Registro!$M$5:$M$804,"PRESO") -> 0
A47: Ricerca perdite | B47: =COUNTIF(Registro!$K$5:$K$804,$A47) -> 4 | C47: =COUNTIFS(Registro!$K$5:$K$804,$A47,Registro!$M$5:$M$804,"PRESO") -> 0 | D47: =COUNTIFS(Registro!$K$5:$K$804,$A47,Registro!$M$5:$M$804,"NON PRESO") -> 0 | E47: =B47-C47-D47 -> 4 | F47: =IFERROR(C47/(C47+D47),0) -> 0 | G47: =SUMIF(Registro!$K$5:$K$804,$A47,Registro!$Q$5:$Q$804) -> 0 | H47: =SUMIFS(Registro!$P$5:$P$804,Registro!$K$5:$K$804,$A47,Registro!$M$5:$M$804,"PRESO") -> 0
A48: Rinnovamento non distruttivo tubazioni (relining) | B48: =COUNTIF(Registro!$K$5:$K$804,$A48) -> 3 | C48: =COUNTIFS(Registro!$K$5:$K$804,$A48,Registro!$M$5:$M$804,"PRESO") -> 0 | D48: =COUNTIFS(Registro!$K$5:$K$804,$A48,Registro!$M$5:$M$804,"NON PRESO") -> 0 | E48: =B48-C48-D48 -> 3 | F48: =IFERROR(C48/(C48+D48),0) -> 0 | G48: =SUMIF(Registro!$K$5:$K$804,$A48,Registro!$Q$5:$Q$804) -> 0 | H48: =SUMIFS(Registro!$P$5:$P$804,Registro!$K$5:$K$804,$A48,Registro!$M$5:$M$804,"PRESO") -> 0
A49: Noleggio bagni chimici | B49: =COUNTIF(Registro!$K$5:$K$804,$A49) -> 0 | C49: =COUNTIFS(Registro!$K$5:$K$804,$A49,Registro!$M$5:$M$804,"PRESO") -> 0 | D49: =COUNTIFS(Registro!$K$5:$K$804,$A49,Registro!$M$5:$M$804,"NON PRESO") -> 0 | E49: =B49-C49-D49 -> 0 | F49: =IFERROR(C49/(C49+D49),0) -> 0 | G49: =SUMIF(Registro!$K$5:$K$804,$A49,Registro!$Q$5:$Q$804) -> 0 | H49: =SUMIFS(Registro!$P$5:$P$804,Registro!$K$5:$K$804,$A49,Registro!$M$5:$M$804,"PRESO") -> 0
A50: Smaltimento rifiuti pericolosi e non pericolosi | B50: =COUNTIF(Registro!$K$5:$K$804,$A50) -> 38 | C50: =COUNTIFS(Registro!$K$5:$K$804,$A50,Registro!$M$5:$M$804,"PRESO") -> 0 | D50: =COUNTIFS(Registro!$K$5:$K$804,$A50,Registro!$M$5:$M$804,"NON PRESO") -> 0 | E50: =B50-C50-D50 -> 38 | F50: =IFERROR(C50/(C50+D50),0) -> 0 | G50: =SUMIF(Registro!$K$5:$K$804,$A50,Registro!$Q$5:$Q$804) -> 0 | H50: =SUMIFS(Registro!$P$5:$P$804,Registro!$K$5:$K$804,$A50,Registro!$M$5:$M$804,"PRESO") -> 0
A51: Locazione cassoni scarrabili | B51: =COUNTIF(Registro!$K$5:$K$804,$A51) -> 0 | C51: =COUNTIFS(Registro!$K$5:$K$804,$A51,Registro!$M$5:$M$804,"PRESO") -> 0 | D51: =COUNTIFS(Registro!$K$5:$K$804,$A51,Registro!$M$5:$M$804,"NON PRESO") -> 0 | E51: =B51-C51-D51 -> 0 | F51: =IFERROR(C51/(C51+D51),0) -> 0 | G51: =SUMIF(Registro!$K$5:$K$804,$A51,Registro!$Q$5:$Q$804) -> 0 | H51: =SUMIFS(Registro!$P$5:$P$804,Registro!$K$5:$K$804,$A51,Registro!$M$5:$M$804,"PRESO") -> 0
A52: Trasporto e smaltimento inerti / terre e rocce da scavo | B52: =COUNTIF(Registro!$K$5:$K$804,$A52) -> 0 | C52: =COUNTIFS(Registro!$K$5:$K$804,$A52,Registro!$M$5:$M$804,"PRESO") -> 0 | D52: =COUNTIFS(Registro!$K$5:$K$804,$A52,Registro!$M$5:$M$804,"NON PRESO") -> 0 | E52: =B52-C52-D52 -> 0 | F52: =IFERROR(C52/(C52+D52),0) -> 0 | G52: =SUMIF(Registro!$K$5:$K$804,$A52,Registro!$Q$5:$Q$804) -> 0 | H52: =SUMIFS(Registro!$P$5:$P$804,Registro!$K$5:$K$804,$A52,Registro!$M$5:$M$804,"PRESO") -> 0
A53: Microraccolta rifiuti | B53: =COUNTIF(Registro!$K$5:$K$804,$A53) -> 0 | C53: =COUNTIFS(Registro!$K$5:$K$804,$A53,Registro!$M$5:$M$804,"PRESO") -> 0 | D53: =COUNTIFS(Registro!$K$5:$K$804,$A53,Registro!$M$5:$M$804,"NON PRESO") -> 0 | E53: =B53-C53-D53 -> 0 | F53: =IFERROR(C53/(C53+D53),0) -> 0 | G53: =SUMIF(Registro!$K$5:$K$804,$A53,Registro!$Q$5:$Q$804) -> 0 | H53: =SUMIFS(Registro!$P$5:$P$804,Registro!$K$5:$K$804,$A53,Registro!$M$5:$M$804,"PRESO") -> 0
A54: Lavorazione rifiuti da costruzione e demolizione (V.A.L. – Cisano sul Neva) | B54: =COUNTIF(Registro!$K$5:$K$804,$A54) -> 0 | C54: =COUNTIFS(Registro!$K$5:$K$804,$A54,Registro!$M$5:$M$804,"PRESO") -> 0 | D54: =COUNTIFS(Registro!$K$5:$K$804,$A54,Registro!$M$5:$M$804,"NON PRESO") -> 0 | E54: =B54-C54-D54 -> 0 | F54: =IFERROR(C54/(C54+D54),0) -> 0 | G54: =SUMIF(Registro!$K$5:$K$804,$A54,Registro!$Q$5:$Q$804) -> 0 | H54: =SUMIFS(Registro!$P$5:$P$804,Registro!$K$5:$K$804,$A54,Registro!$M$5:$M$804,"PRESO") -> 0
A55: Bonifiche ambientali e discariche abusive | B55: =COUNTIF(Registro!$K$5:$K$804,$A55) -> 3 | C55: =COUNTIFS(Registro!$K$5:$K$804,$A55,Registro!$M$5:$M$804,"PRESO") -> 0 | D55: =COUNTIFS(Registro!$K$5:$K$804,$A55,Registro!$M$5:$M$804,"NON PRESO") -> 0 | E55: =B55-C55-D55 -> 3 | F55: =IFERROR(C55/(C55+D55),0) -> 0 | G55: =SUMIF(Registro!$K$5:$K$804,$A55,Registro!$Q$5:$Q$804) -> 0 | H55: =SUMIFS(Registro!$P$5:$P$804,Registro!$K$5:$K$804,$A55,Registro!$M$5:$M$804,"PRESO") -> 0
A56: Rimozione e smaltimento amianto – eternit | B56: =COUNTIF(Registro!$K$5:$K$804,$A56) -> 35 | C56: =COUNTIFS(Registro!$K$5:$K$804,$A56,Registro!$M$5:$M$804,"PRESO") -> 0 | D56: =COUNTIFS(Registro!$K$5:$K$804,$A56,Registro!$M$5:$M$804,"NON PRESO") -> 0 | E56: =B56-C56-D56 -> 35 | F56: =IFERROR(C56/(C56+D56),0) -> 0 | G56: =SUMIF(Registro!$K$5:$K$804,$A56,Registro!$Q$5:$Q$804) -> 0 | H56: =SUMIFS(Registro!$P$5:$P$804,Registro!$K$5:$K$804,$A56,Registro!$M$5:$M$804,"PRESO") -> 0
... A67: Rilevazioni termografiche e certificazione energetica (APE) | B67: =COUNTIF(Registro!$K$5:$K$804,$A67) -> 0 | C67: =COUNTIFS(Registro!$K$5:$K$804,$A67,Registro!$M$5:$M$804,"PRESO") -> 0 | D67: =COUNTIFS(Registro!$K$5:$K$804,$A67,Registro!$M$5:$M$804,"NON PRESO") -> 0 | E67: =B67-C67-D67 -> 0 | F67: =IFERROR(C67/(C67+D67),0) -> 0 | G67: =SUMIF(Registro!$K$5:$K$804,$A67,Registro!$Q$5:$Q$804) -> 0 | H67: =SUMIFS(Registro!$P$5:$P$804,Registro!$K$5:$K$804,$A67,Registro!$M$5:$M$804,"PRESO") -> 0
A68: TOTALE | B68: =SUM(B45:B67) -> 153 | C68: =SUM(C45:C67) -> 0 | D68: =SUM(D45:D67) -> 0 | E68: =SUM(E45:E67) -> 153 | F68: =IFERROR(C68/(C68+D68),0) -> 0 | G68: =SUM(G45:G67) -> 123 | H68: =SUM(H45:H67) -> 0
A70: Per provincia (zona)
A71: Provincia | B71: Contatti | C71: Presi | D71: Non presi | E71: Esito da inserire / in attesa | F71: % presi (sui chiusi) | G71: Costo contatti € | H71: Valore lavori €
A72: SV | B72: =COUNTIF(Registro!$I$5:$I$804,$A72) -> 136 | C72: =COUNTIFS(Registro!$I$5:$I$804,$A72,Registro!$M$5:$M$804,"PRESO") -> 0 | D72: =COUNTIFS(Registro!$I$5:$I$804,$A72,Registro!$M$5:$M$804,"NON PRESO") -> 0 | E72: =B72-C72-D72 -> 136 | F72: =IFERROR(C72/(C72+D72),0) -> 0 | G72: =SUMIF(Registro!$I$5:$I$804,$A72,Registro!$Q$5:$Q$804) -> 66 | H72: =SUMIFS(Registro!$P$5:$P$804,Registro!$I$5:$I$804,$A72,Registro!$M$5:$M$804,"PRESO") -> 0
A73: IM | B73: =COUNTIF(Registro!$I$5:$I$804,$A73) -> 31 | C73: =COUNTIFS(Registro!$I$5:$I$804,$A73,Registro!$M$5:$M$804,"PRESO") -> 0 | D73: =COUNTIFS(Registro!$I$5:$I$804,$A73,Registro!$M$5:$M$804,"NON PRESO") -> 0 | E73: =B73-C73-D73 -> 31 | F73: =IFERROR(C73/(C73+D73),0) -> 0 | G73: =SUMIF(Registro!$I$5:$I$804,$A73,Registro!$Q$5:$Q$804) -> 57 | H73: =SUMIFS(Registro!$P$5:$P$804,Registro!$I$5:$I$804,$A73,Registro!$M$5:$M$804,"PRESO") -> 0
A74: GE | B74: =COUNTIF(Registro!$I$5:$I$804,$A74) -> 8 | C74: =COUNTIFS(Registro!$I$5:$I$804,$A74,Registro!$M$5:$M$804,"PRESO") -> 0 | D74: =COUNTIFS(Registro!$I$5:$I$804,$A74,Registro!$M$5:$M$804,"NON PRESO") -> 0 | E74: =B74-C74-D74 -> 8 | F74: =IFERROR(C74/(C74+D74),0) -> 0 | G74: =SUMIF(Registro!$I$5:$I$804,$A74,Registro!$Q$5:$Q$804) -> 0 | H74: =SUMIFS(Registro!$P$5:$P$804,Registro!$I$5:$I$804,$A74,Registro!$M$5:$M$804,"PRESO") -> 0
A75: AL | B75: =COUNTIF(Registro!$I$5:$I$804,$A75) -> 1 | C75: =COUNTIFS(Registro!$I$5:$I$804,$A75,Registro!$M$5:$M$804,"PRESO") -> 0 | D75: =COUNTIFS(Registro!$I$5:$I$804,$A75,Registro!$M$5:$M$804,"NON PRESO") -> 0 | E75: =B75-C75-D75 -> 1 | F75: =IFERROR(C75/(C75+D75),0) -> 0 | G75: =SUMIF(Registro!$I$5:$I$804,$A75,Registro!$Q$5:$Q$804) -> 0 | H75: =SUMIFS(Registro!$P$5:$P$804,Registro!$I$5:$I$804,$A75,Registro!$M$5:$M$804,"PRESO") -> 0
A76: AT | B76: =COUNTIF(Registro!$I$5:$I$804,$A76) -> 1 | C76: =COUNTIFS(Registro!$I$5:$I$804,$A76,Registro!$M$5:$M$804,"PRESO") -> 0 | D76: =COUNTIFS(Registro!$I$5:$I$804,$A76,Registro!$M$5:$M$804,"NON PRESO") -> 0 | E76: =B76-C76-D76 -> 1 | F76: =IFERROR(C76/(C76+D76),0) -> 0 | G76: =SUMIF(Registro!$I$5:$I$804,$A76,Registro!$Q$5:$Q$804) -> 0 | H76: =SUMIFS(Registro!$P$5:$P$804,Registro!$I$5:$I$804,$A76,Registro!$M$5:$M$804,"PRESO") -> 0
A77: CN | B77: =COUNTIF(Registro!$I$5:$I$804,$A77) -> 1 | C77: =COUNTIFS(Registro!$I$5:$I$804,$A77,Registro!$M$5:$M$804,"PRESO") -> 0 | D77: =COUNTIFS(Registro!$I$5:$I$804,$A77,Registro!$M$5:$M$804,"NON PRESO") -> 0 | E77: =B77-C77-D77 -> 1 | F77: =IFERROR(C77/(C77+D77),0) -> 0 | G77: =SUMIF(Registro!$I$5:$I$804,$A77,Registro!$Q$5:$Q$804) -> 0 | H77: =SUMIFS(Registro!$P$5:$P$804,Registro!$I$5:$I$804,$A77,Registro!$M$5:$M$804,"PRESO") -> 0
A78: MI | B78: =COUNTIF(Registro!$I$5:$I$804,$A78) -> 2 | C78: =COUNTIFS(Registro!$I$5:$I$804,$A78,Registro!$M$5:$M$804,"PRESO") -> 0 | D78: =COUNTIFS(Registro!$I$5:$I$804,$A78,Registro!$M$5:$M$804,"NON PRESO") -> 0 | E78: =B78-C78-D78 -> 2 | F78: =IFERROR(C78/(C78+D78),0) -> 0 | G78: =SUMIF(Registro!$I$5:$I$804,$A78,Registro!$Q$5:$Q$804) -> 0 | H78: =SUMIFS(Registro!$P$5:$P$804,Registro!$I$5:$I$804,$A78,Registro!$M$5:$M$804,"PRESO") -> 0
A79: Altro | B79: =COUNTIF(Registro!$I$5:$I$804,$A79) -> 0 | C79: =COUNTIFS(Registro!$I$5:$I$804,$A79,Registro!$M$5:$M$804,"PRESO") -> 0 | D79: =COUNTIFS(Registro!$I$5:$I$804,$A79,Registro!$M$5:$M$804,"NON PRESO") -> 0 | E79: =B79-C79-D79 -> 0 | F79: =IFERROR(C79/(C79+D79),0) -> 0 | G79: =SUMIF(Registro!$I$5:$I$804,$A79,Registro!$Q$5:$Q$804) -> 0 | H79: =SUMIFS(Registro!$P$5:$P$804,Registro!$I$5:$I$804,$A79,Registro!$M$5:$M$804,"PRESO") -> 0
A80: TOTALE | B80: =SUM(B72:B79) -> 180 | C80: =SUM(C72:C79) -> 0 | D80: =SUM(D72:D79) -> 0 | E80: =SUM(E72:E79) -> 180 | F80: =IFERROR(C80/(C80+D80),0) -> 0 | G80: =SUM(G72:G79) -> 123 | H80: =SUM(H72:H79) -> 0
A82: Per tipo di cliente
A83: Tipo cliente | B83: Contatti | C83: Presi | D83: Non presi | E83: Esito da inserire / in attesa | F83: % presi (sui chiusi) | G83: Costo contatti € | H83: Valore lavori €
A84: Privato | B84: =COUNTIF(Registro!$E$5:$E$804,$A84) -> 126 | C84: =COUNTIFS(Registro!$E$5:$E$804,$A84,Registro!$M$5:$M$804,"PRESO") -> 0 | D84: =COUNTIFS(Registro!$E$5:$E$804,$A84,Registro!$M$5:$M$804,"NON PRESO") -> 0 | E84: =B84-C84-D84 -> 126 | F84: =IFERROR(C84/(C84+D84),0) -> 0 | G84: =SUMIF(Registro!$E$5:$E$804,$A84,Registro!$Q$5:$Q$804) -> 118 | H84: =SUMIFS(Registro!$P$5:$P$804,Registro!$E$5:$E$804,$A84,Registro!$M$5:$M$804,"PRESO") -> 0
A85: Condominio / Amministratore | B85: =COUNTIF(Registro!$E$5:$E$804,$A85) -> 4 | C85: =COUNTIFS(Registro!$E$5:$E$804,$A85,Registro!$M$5:$M$804,"PRESO") -> 0 | D85: =COUNTIFS(Registro!$E$5:$E$804,$A85,Registro!$M$5:$M$804,"NON PRESO") -> 0 | E85: =B85-C85-D85 -> 4 | F85: =IFERROR(C85/(C85+D85),0) -> 0 | G85: =SUMIF(Registro!$E$5:$E$804,$A85,Registro!$Q$5:$Q$804) -> 0 | H85: =SUMIFS(Registro!$P$5:$P$804,Registro!$E$5:$E$804,$A85,Registro!$M$5:$M$804,"PRESO") -> 0
A86: Impresa edile / Artigiano | B86: =COUNTIF(Registro!$E$5:$E$804,$A86) -> 30 | C86: =COUNTIFS(Registro!$E$5:$E$804,$A86,Registro!$M$5:$M$804,"PRESO") -> 0 | D86: =COUNTIFS(Registro!$E$5:$E$804,$A86,Registro!$M$5:$M$804,"NON PRESO") -> 0 | E86: =B86-C86-D86 -> 30 | F86: =IFERROR(C86/(C86+D86),0) -> 0 | G86: =SUMIF(Registro!$E$5:$E$804,$A86,Registro!$Q$5:$Q$804) -> 0 | H86: =SUMIFS(Registro!$P$5:$P$804,Registro!$E$5:$E$804,$A86,Registro!$M$5:$M$804,"PRESO") -> 0
A87: Azienda / Società | B87: =COUNTIF(Registro!$E$5:$E$804,$A87) -> 7 | C87: =COUNTIFS(Registro!$E$5:$E$804,$A87,Registro!$M$5:$M$804,"PRESO") -> 0 | D87: =COUNTIFS(Registro!$E$5:$E$804,$A87,Registro!$M$5:$M$804,"NON PRESO") -> 0 | E87: =B87-C87-D87 -> 7 | F87: =IFERROR(C87/(C87+D87),0) -> 0 | G87: =SUMIF(Registro!$E$5:$E$804,$A87,Registro!$Q$5:$Q$804) -> 5 | H87: =SUMIFS(Registro!$P$5:$P$804,Registro!$E$5:$E$804,$A87,Registro!$M$5:$M$804,"PRESO") -> 0
A88: Attività / Turismo | B88: =COUNTIF(Registro!$E$5:$E$804,$A88) -> 16 | C88: =COUNTIFS(Registro!$E$5:$E$804,$A88,Registro!$M$5:$M$804,"PRESO") -> 0 | D88: =COUNTIFS(Registro!$E$5:$E$804,$A88,Registro!$M$5:$M$804,"NON PRESO") -> 0 | E88: =B88-C88-D88 -> 16 | F88: =IFERROR(C88/(C88+D88),0) -> 0 | G88: =SUMIF(Registro!$E$5:$E$804,$A88,Registro!$Q$5:$Q$804) -> 0 | H88: =SUMIFS(Registro!$P$5:$P$804,Registro!$E$5:$E$804,$A88,Registro!$M$5:$M$804,"PRESO") -> 0
A89: Ente pubblico | B89: =COUNTIF(Registro!$E$5:$E$804,$A89) -> 1 | C89: =COUNTIFS(Registro!$E$5:$E$804,$A89,Registro!$M$5:$M$804,"PRESO") -> 0 | D89: =COUNTIFS(Registro!$E$5:$E$804,$A89,Registro!$M$5:$M$804,"NON PRESO") -> 0 | E89: =B89-C89-D89 -> 1 | F89: =IFERROR(C89/(C89+D89),0) -> 0 | G89: =SUMIF(Registro!$E$5:$E$804,$A89,Registro!$Q$5:$Q$804) -> 0 | H89: =SUMIFS(Registro!$P$5:$P$804,Registro!$E$5:$E$804,$A89,Registro!$M$5:$M$804,"PRESO") -> 0
A90: Nautica / Porto | B90: =COUNTIF(Registro!$E$5:$E$804,$A90) -> 0 | C90: =COUNTIFS(Registro!$E$5:$E$804,$A90,Registro!$M$5:$M$804,"PRESO") -> 0 | D90: =COUNTIFS(Registro!$E$5:$E$804,$A90,Registro!$M$5:$M$804,"NON PRESO") -> 0 | E90: =B90-C90-D90 -> 0 | F90: =IFERROR(C90/(C90+D90),0) -> 0 | G90: =SUMIF(Registro!$E$5:$E$804,$A90,Registro!$Q$5:$Q$804) -> 0 | H90: =SUMIFS(Registro!$P$5:$P$804,Registro!$E$5:$E$804,$A90,Registro!$M$5:$M$804,"PRESO") -> 0
A91: Altro | B91: =COUNTIF(Registro!$E$5:$E$804,$A91) -> 0 | C91: =COUNTIFS(Registro!$E$5:$E$804,$A91,Registro!$M$5:$M$804,"PRESO") -> 0 | D91: =COUNTIFS(Registro!$E$5:$E$804,$A91,Registro!$M$5:$M$804,"NON PRESO") -> 0 | E91: =B91-C91-D91 -> 0 | F91: =IFERROR(C91/(C91+D91),0) -> 0 | G91: =SUMIF(Registro!$E$5:$E$804,$A91,Registro!$Q$5:$Q$804) -> 0 | H91: =SUMIFS(Registro!$P$5:$P$804,Registro!$E$5:$E$804,$A91,Registro!$M$5:$M$804,"PRESO") -> 0
A92: TOTALE | B92: =SUM(B84:B91) -> 184 | C92: =SUM(C84:C91) -> 0 | D92: =SUM(D84:D91) -> 0 | E92: =SUM(E84:E91) -> 184 | F92: =IFERROR(C92/(C92+D92),0) -> 0 | G92: =SUM(G84:G91) -> 123 | H92: =SUM(H84:H91) -> 0
A94: Per commerciale (codice)
A95: Commerciale | B95: Contatti | C95: Presi | D95: Non presi | E95: Esito da inserire / in attesa | F95: % presi (sui chiusi) | G95: Costo contatti € | H95: Valore lavori €
A96: 1 | B96: =COUNTIF(Registro!$R$5:$R$804,$A96) -> 6 | C96: =COUNTIFS(Registro!$R$5:$R$804,$A96,Registro!$M$5:$M$804,"PRESO") -> 0 | D96: =COUNTIFS(Registro!$R$5:$R$804,$A96,Registro!$M$5:$M$804,"NON PRESO") -> 0 | E96: =B96-C96-D96 -> 6 | F96: =IFERROR(C96/(C96+D96),0) -> 0 | G96: =SUMIF(Registro!$R$5:$R$804,$A96,Registro!$Q$5:$Q$804) -> 0 | H96: =SUMIFS(Registro!$P$5:$P$804,Registro!$R$5:$R$804,$A96,Registro!$M$5:$M$804,"PRESO") -> 0
A97: 4 | B97: =COUNTIF(Registro!$R$5:$R$804,$A97) -> 73 | C97: =COUNTIFS(Registro!$R$5:$R$804,$A97,Registro!$M$5:$M$804,"PRESO") -> 0 | D97: =COUNTIFS(Registro!$R$5:$R$804,$A97,Registro!$M$5:$M$804,"NON PRESO") -> 0 | E97: =B97-C97-D97 -> 73 | F97: =IFERROR(C97/(C97+D97),0) -> 0 | G97: =SUMIF(Registro!$R$5:$R$804,$A97,Registro!$Q$5:$Q$804) -> 0 | H97: =SUMIFS(Registro!$P$5:$P$804,Registro!$R$5:$R$804,$A97,Registro!$M$5:$M$804,"PRESO") -> 0
A98: 11 | B98: =COUNTIF(Registro!$R$5:$R$804,$A98) -> 18 | C98: =COUNTIFS(Registro!$R$5:$R$804,$A98,Registro!$M$5:$M$804,"PRESO") -> 0 | D98: =COUNTIFS(Registro!$R$5:$R$804,$A98,Registro!$M$5:$M$804,"NON PRESO") -> 0 | E98: =B98-C98-D98 -> 18 | F98: =IFERROR(C98/(C98+D98),0) -> 0 | G98: =SUMIF(Registro!$R$5:$R$804,$A98,Registro!$Q$5:$Q$804) -> 0 | H98: =SUMIFS(Registro!$P$5:$P$804,Registro!$R$5:$R$804,$A98,Registro!$M$5:$M$804,"PRESO") -> 0
A99: 33 | B99: =COUNTIF(Registro!$R$5:$R$804,$A99) -> 17 | C99: =COUNTIFS(Registro!$R$5:$R$804,$A99,Registro!$M$5:$M$804,"PRESO") -> 0 | D99: =COUNTIFS(Registro!$R$5:$R$804,$A99,Registro!$M$5:$M$804,"NON PRESO") -> 0 | E99: =B99-C99-D99 -> 17 | F99: =IFERROR(C99/(C99+D99),0) -> 0 | G99: =SUMIF(Registro!$R$5:$R$804,$A99,Registro!$Q$5:$Q$804) -> 0 | H99: =SUMIFS(Registro!$P$5:$P$804,Registro!$R$5:$R$804,$A99,Registro!$M$5:$M$804,"PRESO") -> 0
A100: 34 | B100: =COUNTIF(Registro!$R$5:$R$804,$A100) -> 41 | C100: =COUNTIFS(Registro!$R$5:$R$804,$A100,Registro!$M$5:$M$804,"PRESO") -> 0 | D100: =COUNTIFS(Registro!$R$5:$R$804,$A100,Registro!$M$5:$M$804,"NON PRESO") -> 0 | E100: =B100-C100-D100 -> 41 | F100: =IFERROR(C100/(C100+D100),0) -> 0 | G100: =SUMIF(Registro!$R$5:$R$804,$A100,Registro!$Q$5:$Q$804) -> 0 | H100: =SUMIFS(Registro!$P$5:$P$804,Registro!$R$5:$R$804,$A100,Registro!$M$5:$M$804,"PRESO") -> 0
A101: 35 | B101: =COUNTIF(Registro!$R$5:$R$804,$A101) -> 3 | C101: =COUNTIFS(Registro!$R$5:$R$804,$A101,Registro!$M$5:$M$804,"PRESO") -> 0 | D101: =COUNTIFS(Registro!$R$5:$R$804,$A101,Registro!$M$5:$M$804,"NON PRESO") -> 0 | E101: =B101-C101-D101 -> 3 | F101: =IFERROR(C101/(C101+D101),0) -> 0 | G101: =SUMIF(Registro!$R$5:$R$804,$A101,Registro!$Q$5:$Q$804) -> 0 | H101: =SUMIFS(Registro!$P$5:$P$804,Registro!$R$5:$R$804,$A101,Registro!$M$5:$M$804,"PRESO") -> 0
A102: 38 | B102: =COUNTIF(Registro!$R$5:$R$804,$A102) -> 1 | C102: =COUNTIFS(Registro!$R$5:$R$804,$A102,Registro!$M$5:$M$804,"PRESO") -> 0 | D102: =COUNTIFS(Registro!$R$5:$R$804,$A102,Registro!$M$5:$M$804,"NON PRESO") -> 0 | E102: =B102-C102-D102 -> 1 | F102: =IFERROR(C102/(C102+D102),0) -> 0 | G102: =SUMIF(Registro!$R$5:$R$804,$A102,Registro!$Q$5:$Q$804) -> 0 | H102: =SUMIFS(Registro!$P$5:$P$804,Registro!$R$5:$R$804,$A102,Registro!$M$5:$M$804,"PRESO") -> 0
A103: TOTALE | B103: =SUM(B96:B102) -> 159 | C103: =SUM(C96:C102) -> 0 | D103: =SUM(D96:D102) -> 0 | E103: =SUM(E96:E102) -> 159 | F103: =IFERROR(C103/(C103+D103),0) -> 0 | G103: =SUM(G96:G102) -> 0 | H103: =SUM(H96:H102) -> 0
A105: Incrocio: contatti per area e fonte
A106: Area | B106: PgCasa (Italiaonline) | C106: Italiaonline | D106: Internet | E106: Passaparola | F106: Altre fonti | G106: Totale
A107: SPURGHI E RETI | B107: =COUNTIFS(Registro!$J$5:$J$804,$A107,Registro!$B$5:$B$804,B$106) -> 7 | C107: =COUNTIFS(Registro!$J$5:$J$804,$A107,Registro!$B$5:$B$804,C$106) -> 5 | D107: =COUNTIFS(Registro!$J$5:$J$804,$A107,Registro!$B$5:$B$804,D$106) -> 3 | E107: =COUNTIFS(Registro!$J$5:$J$804,$A107,Registro!$B$5:$B$804,E$106) -> 12 | F107: =G107-SUM(B107:E107) -> 3 | G107: =COUNTIF(Registro!$J$5:$J$804,$A107) -> 30
A108: RIFIUTI | B108: =COUNTIFS(Registro!$J$5:$J$804,$A108,Registro!$B$5:$B$804,B$106) -> 0 | C108: =COUNTIFS(Registro!$J$5:$J$804,$A108,Registro!$B$5:$B$804,C$106) -> 8 | D108: =COUNTIFS(Registro!$J$5:$J$804,$A108,Registro!$B$5:$B$804,D$106) -> 15 | E108: =COUNTIFS(Registro!$J$5:$J$804,$A108,Registro!$B$5:$B$804,E$106) -> 13 | F108: =G108-SUM(B108:E108) -> 2 | G108: =COUNTIF(Registro!$J$5:$J$804,$A108) -> 38
A109: BONIFICHE | B109: =COUNTIFS(Registro!$J$5:$J$804,$A109,Registro!$B$5:$B$804,B$106) -> 0 | C109: =COUNTIFS(Registro!$J$5:$J$804,$A109,Registro!$B$5:$B$804,C$106) -> 10 | D109: =COUNTIFS(Registro!$J$5:$J$804,$A109,Registro!$B$5:$B$804,D$106) -> 7 | E109: =COUNTIFS(Registro!$J$5:$J$804,$A109,Registro!$B$5:$B$804,E$106) -> 20 | F109: =G109-SUM(B109:E109) -> 1 | G109: =COUNTIF(Registro!$J$5:$J$804,$A109) -> 38
A110: DISINFESTAZIONE | B110: =COUNTIFS(Registro!$J$5:$J$804,$A110,Registro!$B$5:$B$804,B$106) -> 9 | C110: =COUNTIFS(Registro!$J$5:$J$804,$A110,Registro!$B$5:$B$804,C$106) -> 3 | D110: =COUNTIFS(Registro!$J$5:$J$804,$A110,Registro!$B$5:$B$804,D$106) -> 4 | E110: =COUNTIFS(Registro!$J$5:$J$804,$A110,Registro!$B$5:$B$804,E$106) -> 16 | F110: =G110-SUM(B110:E110) -> 1 | G110: =COUNTIF(Registro!$J$5:$J$804,$A110) -> 33
A111: IGIENE IMPIANTI | B111: =COUNTIFS(Registro!$J$5:$J$804,$A111,Registro!$B$5:$B$804,B$106) -> 0 | C111: =COUNTIFS(Registro!$J$5:$J$804,$A111,Registro!$B$5:$B$804,C$106) -> 7 | D111: =COUNTIFS(Registro!$J$5:$J$804,$A111,Registro!$B$5:$B$804,D$106) -> 3 | E111: =COUNTIFS(Registro!$J$5:$J$804,$A111,Registro!$B$5:$B$804,E$106) -> 4 | F111: =G111-SUM(B111:E111) -> 0 | G111: =COUNTIF(Registro!$J$5:$J$804,$A111) -> 14
A112: NAUTICA | B112: =COUNTIFS(Registro!$J$5:$J$804,$A112,Registro!$B$5:$B$804,B$106) -> 0 | C112: =COUNTIFS(Registro!$J$5:$J$804,$A112,Registro!$B$5:$B$804,C$106) -> 0 | D112: =COUNTIFS(Registro!$J$5:$J$804,$A112,Registro!$B$5:$B$804,D$106) -> 0 | E112: =COUNTIFS(Registro!$J$5:$J$804,$A112,Registro!$B$5:$B$804,E$106) -> 0 | F112: =G112-SUM(B112:E112) -> 0 | G112: =COUNTIF(Registro!$J$5:$J$804,$A112) -> 0
A113: CONSULENZA | B113: =COUNTIFS(Registro!$J$5:$J$804,$A113,Registro!$B$5:$B$804,B$106) -> 0 | C113: =COUNTIFS(Registro!$J$5:$J$804,$A113,Registro!$B$5:$B$804,C$106) -> 0 | D113: =COUNTIFS(Registro!$J$5:$J$804,$A113,Registro!$B$5:$B$804,D$106) -> 0 | E113: =COUNTIFS(Registro!$J$5:$J$804,$A113,Registro!$B$5:$B$804,E$106) -> 0 | F113: =G113-SUM(B113:E113) -> 0 | G113: =COUNTIF(Registro!$J$5:$J$804,$A113) -> 0
A114: DA SPECIFICARE | B114: =COUNTIFS(Registro!$J$5:$J$804,$A114,Registro!$B$5:$B$804,B$106) -> 0 | C114: =COUNTIFS(Registro!$J$5:$J$804,$A114,Registro!$B$5:$B$804,C$106) -> 7 | D114: =COUNTIFS(Registro!$J$5:$J$804,$A114,Registro!$B$5:$B$804,D$106) -> 5 | E114: =COUNTIFS(Registro!$J$5:$J$804,$A114,Registro!$B$5:$B$804,E$106) -> 18 | F114: =G114-SUM(B114:E114) -> 1 | G114: =COUNTIF(Registro!$J$5:$J$804,$A114) -> 31
A116: Per mese (2026)
A117: Mese | B117: Contatti | C117: di cui Italiaonline + PgCasa | D117: Presi | E117: Non presi
A118: Gennaio | B118: =COUNTIFS(Registro!$A$5:$A$804,">="&DATE(2026,1,1),Registro!$A$5:$A$804,"<"&DATE(2026,2,1)) -> 15 | C118: =COUNTIFS(Registro!$A$5:$A$804,">="&DATE(2026,1,1),Registro!$A$5:$A$804,"<"&DATE(2026,2,1),Registro!$B$5:$B$804,"Italiaonline")+COUNTIFS(Registro!$A$5:$A$804,">="&DATE(2026,1,1),Registro!$A$5:$A$804,"<"&DATE(2026,2,1),Registro!$B$5:$B$804,"PgCasa (Italiaonline)") -> 8 | D118: =COUNTIFS(Registro!$A$5:$A$804,">="&DATE(2026,1,1),Registro!$A$5:$A$804,"<"&DATE(2026,2,1),Registro!$M$5:$M$804,"PRESO") -> 0 | E118: =COUNTIFS(Registro!$A$5:$A$804,">="&DATE(2026,1,1),Registro!$A$5:$A$804,"<"&DATE(2026,2,1),Registro!$M$5:$M$804,"NON PRESO") -> 0
A119: Febbraio | B119: =COUNTIFS(Registro!$A$5:$A$804,">="&DATE(2026,2,1),Registro!$A$5:$A$804,"<"&DATE(2026,3,1)) -> 11 | C119: =COUNTIFS(Registro!$A$5:$A$804,">="&DATE(2026,2,1),Registro!$A$5:$A$804,"<"&DATE(2026,3,1),Registro!$B$5:$B$804,"Italiaonline")+COUNTIFS(Registro!$A$5:$A$804,">="&DATE(2026,2,1),Registro!$A$5:$A$804,"<"&DATE(2026,3,1),Registro!$B$5:$B$804,"PgCasa (Italiaonline)") -> 8 | D119: =COUNTIFS(Registro!$A$5:$A$804,">="&DATE(2026,2,1),Registro!$A$5:$A$804,"<"&DATE(2026,3,1),Registro!$M$5:$M$804,"PRESO") -> 0 | E119: =COUNTIFS(Registro!$A$5:$A$804,">="&DATE(2026,2,1),Registro!$A$5:$A$804,"<"&DATE(2026,3,1),Registro!$M$5:$M$804,"NON PRESO") -> 0
A120: Marzo | B120: =COUNTIFS(Registro!$A$5:$A$804,">="&DATE(2026,3,1),Registro!$A$5:$A$804,"<"&DATE(2026,4,1)) -> 22 | C120: =COUNTIFS(Registro!$A$5:$A$804,">="&DATE(2026,3,1),Registro!$A$5:$A$804,"<"&DATE(2026,4,1),Registro!$B$5:$B$804,"Italiaonline")+COUNTIFS(Registro!$A$5:$A$804,">="&DATE(2026,3,1),Registro!$A$5:$A$804,"<"&DATE(2026,4,1),Registro!$B$5:$B$804,"PgCasa (Italiaonline)") -> 4 | D120: =COUNTIFS(Registro!$A$5:$A$804,">="&DATE(2026,3,1),Registro!$A$5:$A$804,"<"&DATE(2026,4,1),Registro!$M$5:$M$804,"PRESO") -> 0 | E120: =COUNTIFS(Registro!$A$5:$A$804,">="&DATE(2026,3,1),Registro!$A$5:$A$804,"<"&DATE(2026,4,1),Registro!$M$5:$M$804,"NON PRESO") -> 0
...

Sheet Canali pubblicitari
A1: Canali pubblicitari 2026: costi e contatti ricevuti
A2: Costi da contratti (Italiaonline 11/12/2025, CIBRA 26/02/2025) ed elenco striscioni Contini 2026; contatti dal Registro (gen–22 set 2026)
A4: Canale | B4: Fornitore / contratto | C4: Cosa comprende | D4: Zona | E4: Costo annuo € (IVA escl.) | F4: Contatti 2026 nel registro | G4: Costo per contatto € | H4: Note
A5: Italiaonline – pacchetto digitale | B5: Italiaonline, ordine B2996193-0 del 11/12/2025 (365 gg, 7 rate SDD dal 27/02/2026) | C5: InRete Standard+ 1.099; Sito AI Extra 999; Business Contact scheda 50 + sito 449; Google Ads set-up 649 + budget 4.400; PgCasa ScegliTu 50 + ricarica 150; sconto 1° anno −753,56 | D5: Imperia, Savona, Genova (Google Ads) | E5: 7092.44 | F5: =COUNTIFS(Registro!$B$5:$B$804,"Italiaonline",Registro!$A$5:$A$804,">="&DATE(2026,1,1))+COUNTIFS(Registro!$B$5:$B$804,"PgCasa (Italiaonline)",Registro!$A$5:$A$804,">="&DATE(2026,1,1)) -> 51 | G5: =IF(OR(E5="",E5=0),"",IFERROR(E5/F5,"nessun contatto")) -> 139.06745
A6: Internet – sito / Google | B6: Sito AI Extra e Google Ads compresi nel contratto Italiaonline | C6: Richieste arrivate da 'Internet' (nostro sito, Google, Pagine Gialle) | D6: Tutte | E6: 0 | F6: =COUNTIFS(Registro!$B$5:$B$804,"Internet",Registro!$A$5:$A$804,">="&DATE(2026,1,1))+COUNTIFS(Registro!$B$5:$B$804,"Pagine Gialle",Registro!$A$5:$A$804,">="&DATE(2026,1,1)) -> 38 | G6: =IF(OR(E6="",E6=0),"",IFERROR(E6/F6,"nessun contatto"))
A7: TOTALE DIGITALE (Italiaonline + Internet) | E7: =E5+E6 -> 7092.44 | F7: =F5+F6 -> 89 | G7: =IF(OR(E7="",E7=0),"",IFERROR(E7/F7,"nessun contatto")) -> 79.690337
A8: Cartelloni CIBRA Genova | B8: CIBRA Pubblicità, contratto 26/02/2025, 5 anni | C8: 2 impianti monofacciali: C.C. Coop Sestri Ponente (imp. 404) e Coop Pegli (imp. 483); sostituisce il cartello di Albenga (contratto 103509) | D8: Genova | E8: 2185 | F8: =COUNTIFS(Registro!$T$5:$T$804,"Genova",Registro!$A$5:$A$804,">="&DATE(2026,1,1)) -> 7 | G8: =IF(OR(E8="",E8=0),"",IFERROR(E8/F8,"nessun contatto")) -> 312.14286
A9: Cartellone CIBRA Imperia (Coop) | B9: CIBRA – da elenco striscioni (approvato 2025) | C9: Cartellone presso Coop Imperia | D9: Imperia | F9: =COUNTIFS(Registro!$T$5:$T$804,"Imperia",Registro!$A$5:$A$804,">="&DATE(2026,1,1)) -> 8 | G9: =IF(OR(E9="",E9=0),"",IFERROR(E9/F9,"nessun contatto"))
A10: Striscioni campi sportivi | B10: Vari (vedi foglio Striscioni vs chiamate) | C10: Striscioni 2x1, 2x3, 5x3 presso campi e palestre | D10: Sanremo, Taggia, S.Lorenzo, Imperia, Loano, Borghetto, Albenga | E10: ='Striscioni vs chiamate'!D22 -> 7300 | F10: =COUNTIFS(Registro!$T$5:$T$804,"<>Zone senza striscioni/cartelloni",Registro!$T$5:$T$804,"<>Genova",Registro!$A$5:$A$804,">="&DATE(2026,1,1)) -> 42 | G10: =IF(OR(E10="",E10=0),"",IFERROR(E10/F10,"nessun contatto")) -> 173.80952
A11: Pubblicità automezzi | B11: Interna | C11: Scritte sui camion | D11: Tutte | E11: 0 | F11: =COUNTIFS(Registro!$B$5:$B$804,"Pubblicità Automezzi",Registro!$A$5:$A$804,">="&DATE(2026,1,1)) -> 1 | G11: =IF(OR(E11="",E11=0),"",IFERROR(E11/F11,"nessun contatto"))
A12: Bus | B12: — | C12: Pubblicità su autobus | D12: — | F12: =COUNTIFS(Registro!$B$5:$B$804,"Bus",Registro!$A$5:$A$804,">="&DATE(2026,1,1)) -> 1 | G12: =IF(OR(E12="",E12=0),"",IFERROR(E12/F12,"nessun contatto"))
A13: Manifesti derattizzazione | B13: Interna | C13: Manifesti/cartelli derattizzazione | D13: — | F13: =COUNTIFS(Registro!$B$5:$B$804,"Manifesti deratt.",Registro!$A$5:$A$804,">="&DATE(2026,1,1)) -> 1 | G13: =IF(OR(E13="",E13=0),"",IFERROR(E13/F13,"nessun contatto"))
A14: Quotidiani online | B14: — | C14: Banner su quotidiani online | D14: — | F14: =COUNTIFS(Registro!$B$5:$B$804,"Quotidiani Online",Registro!$A$5:$A$804,">="&DATE(2026,1,1)) -> 2 | G14: =IF(OR(E14="",E14=0),"",IFERROR(E14/F14,"nessun contatto"))
A15: Imprese Ambiente | B15: — | C15: Portale/elenco | D15: — | F15: =COUNTIFS(Registro!$B$5:$B$804,"Imprese Ambiente",Registro!$A$5:$A$804,">="&DATE(2026,1,1)) -> 1 | G15: =IF(OR(E15="",E15=0),"",IFERROR(E15/F15,"nessun contatto"))
A16: Passaparola | B16: — | C16: Clienti, comuni, ecocentri, impianti che ci consigliano | D16: Tutte | E16: 0 | F16: =COUNTIFS(Registro!$B$5:$B$804,"Passaparola",Registro!$A$5:$A$804,">="&DATE(2026,1,1)) -> 83 | G16: =IF(OR(E16="",E16=0),"",IFERROR(E16/F16,"nessun contatto"))
A18: Spesa pubblicitaria da bilancio (conto 68/05/290 PUBBLICITA')
A19: Anno | B19: Pubblicità € | C19: Ricavi totali € | D19: Pubblicità % ricavi
A20: 2023 | B20: 13669.79 | C20: 3041059.5 | D20: =B20/C20 -> 0.0044950749
A21: 2024 | B21: 29322.1 | C21: 2737076.7 | D21: =B21/C21 -> 0.010712926
A22: 2025 | B22: 22795.01 | C22: 2351765 | D22: =B22/C22 -> 0.0096927246
A23: 2026 impegnato (Italiaonline + CIBRA) | B23: =7999.94+E8 -> 10184.94 | E23: Fonte: Bilancio comparato 2023-24-25 (conto economico). 2026: somma contratti noti, striscioni esclusi.

Sheet Striscioni vs chiamate
A1: Striscioni e cartelloni: confronto con il registro chiamate
A2: Fonte: 'Elenco striscioni e pubblicità aggiornato 2026 Contini'. Le chiamate sono quelle del Registro (gen–set 2026) dai comuni della zona
A4: Dove | B4: Zona | C4: Tipo | D4: Costo € (da elenco) | E4: Periodo | F4: Stato / pagamento | G4: Responsabile | H4: Zona registro | I4: Chiamate 2026 dalla zona | J4: di cui dichiarate 'striscione'
A5: RVS Polisportiva | B5: Valle Armea Sanremo palestra | C5: Striscione 2x1 (fisso) | D5: 250 | E5: 2023/2024 | F5: Da rimettere e ripagare 2026 | G5: Massimo | H5: Sanremo / Taggia / S.Lorenzo | I5: =COUNTIFS(Registro!$T$5:$T$804,H5,Registro!$A$5:$A$804,">="&DATE(2026,1,1)) -> 14 | J5: 0
A6: NLP Polisportiva | B6: Valle Armea Sanremo campo B | C6: Striscione vecchio forato | D6: 0 | E6: 2023/2024 | F6: RIMOSSO (strappato) – gratis | G6: Massimo | H6: Sanremo / Taggia / S.Lorenzo | I6: =COUNTIFS(Registro!$T$5:$T$804,H6,Registro!$A$5:$A$804,">="&DATE(2026,1,1)) -> 14 | J6: 0
A7: Tennis Club Arma di Taggia | B7: Arma di Taggia campo sportivo | C7: Striscione 2x3 plastificato | D7: 300 | E7: 2024/2025 | F7: Consegnato; da pagare 2027 | G7: Massimo | H7: Sanremo / Taggia / S.Lorenzo | I7: =COUNTIFS(Registro!$T$5:$T$804,H7,Registro!$A$5:$A$804,">="&DATE(2026,1,1)) -> 14 | J7: 0
A8: BC Station | B8: San Lorenzo al Mare / campo Riva | C8: Striscione 5x3 forato | D8: 700 | E8: 2024/2026 | F8: Concluso – scontato su fattura | G8: Massimo | H8: Sanremo / Taggia / S.Lorenzo | I8: =COUNTIFS(Registro!$T$5:$T$804,H8,Registro!$A$5:$A$804,">="&DATE(2026,1,1)) -> 14 | J8: 0
A9: RVS Polisportiva | B9: Sanremo palestra Villa Citera | C9: Striscione | D9: 250 | E9: 2024/2025 | F9: Messo – pagato 300 € nel 2026 | G9: Massimo | H9: Sanremo / Taggia / S.Lorenzo | I9: =COUNTIFS(Registro!$T$5:$T$804,H9,Registro!$A$5:$A$804,">="&DATE(2026,1,1)) -> 14 | J9: 0
A10: Imperia Volley | B10: Imperia (in auto da consegnare) | C10: Striscione 2x1 | D10: 300 | E10: 2025/2026 | F10: Da approvare – da pagare 2025 e 2026 | G10: Massimo | H10: Imperia | I10: =COUNTIFS(Registro!$T$5:$T$804,H10,Registro!$A$5:$A$804,">="&DATE(2026,1,1)) -> 8 | J10: 0
A11: Campo Sportivo Borghetto S.S. | B11: Borghetto S.S. | C11: Striscione da prendere | D11: 250 | E11: 2024/2025 | F11: DA METTERE – fermo, non pagato | G11: Sergio Val | H11: Loano / Borghetto / Pietra | I11: =COUNTIFS(Registro!$T$5:$T$804,H11,Registro!$A$5:$A$804,">="&DATE(2026,1,1)) -> 16 | J11: 0
A12: Campo Sportivo Loano | B12: Loano | C12: Striscioni 2x1 nuovi | D12: 250 | E12: 2024/2025 | F12: Da mettere/approvare (+ ritiro 4 big bag macerie in cambio) | G12: Andrea Bac | H12: Loano / Borghetto / Pietra | I12: =COUNTIFS(Registro!$T$5:$T$804,H12,Registro!$A$5:$A$804,">="&DATE(2026,1,1)) -> 16 | J12: 0
A13: ASD Ranzi | B13: Sagra Ranzi (Pietra Ligure) | C13: Provvisorio | E13: 2025/2026 | F13: Riportato Baccino | G13: Andrea Bac | H13: Loano / Borghetto / Pietra | I13: =COUNTIFS(Registro!$T$5:$T$804,H13,Registro!$A$5:$A$804,">="&DATE(2026,1,1)) -> 16 | J13: 0
A14: ASD Pontelungo | B14: Stadio Albenga-Pontelungo | C14: Striscione 5x3 forato GRANDE | D14: 5000 | E14: ott 2025–2027 | F14: Da concordare: 5.000 € per 3 anni a rate | G14: Massimo | H14: Albenga | I14: =COUNTIFS(Registro!$T$5:$T$804,H14,Registro!$A$5:$A$804,">="&DATE(2026,1,1)) -> 4 | J14: 0
A15: V.A.L. | B15: Cisano sul Neva | C15: Striscione 5x3 nuovo | E15: 2025/2026 | F15: In essere – da fare Sergio | G15: Sergio Val | H15: Cisano (V.A.L.) | I15: =COUNTIFS(Registro!$T$5:$T$804,H15,Registro!$A$5:$A$804,">="&DATE(2026,1,1)) -> 0 | J15: 0
A16: Corderia Nazionale | B16: Genova | C16: — | E16: dal 01/09/2024 | F16: Chiuso – 5% su eventuali lavori | G16: Massimo | H16: Genova | I16: =COUNTIFS(Registro!$T$5:$T$804,H16,Registro!$A$5:$A$804,">="&DATE(2026,1,1)) -> 7 | J16: 0
A17: Aut. Porto Sestri Ponente | B17: Genova aeroporto | C17: Cartellone fisso + volantino + online | D17: 1200 | E17: annuale | F17: Stato non indicato | G17: — | H17: Genova | I17: =COUNTIFS(Registro!$T$5:$T$804,H17,Registro!$A$5:$A$804,">="&DATE(2026,1,1)) -> 7 | J17: 0
A18: CIBRA | B18: Coop Imperia | C18: Cartellone | E18: 2025 | F18: Approvata – in essere | G18: Kikko | H18: Imperia | I18: =COUNTIFS(Registro!$T$5:$T$804,H18,Registro!$A$5:$A$804,">="&DATE(2026,1,1)) -> 8 | J18: 0
A19: CIBRA | B19: Coop Sestri Ponente + Coop Pegli (Genova) | C19: 2 cartelloni monofacciali | D19: 2185 | E19: 2025–2030 | F19: In essere (contratto 26/02/2025) | G19: Kikko / Pasini | H19: Genova | I19: =COUNTIFS(Registro!$T$5:$T$804,H19,Registro!$A$5:$A$804,">="&DATE(2026,1,1)) -> 7 | J19: 0
A20: Italiaonline PgCasa + Google Ads | B20: Imperia, Savona, Genova | C20: Campagna digitale | D20: 3700 | E20: 2025 | F20: Da riapprovare (vedi contratto 2026: 7.999,94 €) | G20: Massimo / Kikko | H20: Zone senza striscioni/cartelloni | I20: vedi foglio Canali | J20: 0
A22: Totale striscioni campi sportivi (da elenco) | D22: =SUM(D5:D14) -> 7300
A23: Nota: Pontelungo (5.000 €) è su 3 anni; molti importi sono 'da pagare' o 'da approvare'.
A26: Chiamate 2026 per zona e provenienza dichiarata
A27: Zona | B27: Italiaonline | C27: PgCasa (Italiaonline) | D27: Internet | E27: Passaparola | F27: Altre | G27: Totale | H27: Servizio più richiesto
A28: Sanremo / Taggia / S.Lorenzo | B28: =COUNTIFS(Registro!$T$5:$T$804,$A28,Registro!$B$5:$B$804,"Italiaonline",Registro!$A$5:$A$804,">="&DATE(2026,1,1)) -> 4 | C28: =COUNTIFS(Registro!$T$5:$T$804,$A28,Registro!$B$5:$B$804,"PgCasa (Italiaonline)",Registro!$A$5:$A$804,">="&DATE(2026,1,1)) -> 3 | D28: =COUNTIFS(Registro!$T$5:$T$804,$A28,Registro!$B$5:$B$804,"Internet",Registro!$A$5:$A$804,">="&DATE(2026,1,1)) -> 0 | E28: =COUNTIFS(Registro!$T$5:$T$804,$A28,Registro!$B$5:$B$804,"Passaparola",Registro!$A$5:$A$804,">="&DATE(2026,1,1)) -> 7 | F28: =G28-SUM(B28:E28) -> 0 | G28: =COUNTIFS(Registro!$T$5:$T$804,$A28,Registro!$A$5:$A$804,">="&DATE(2026,1,1)) -> 14 | H28: Bonifiche (7 su 14)
A29: Imperia | B29: =COUNTIFS(Registro!$T$5:$T$804,$A29,Registro!$B$5:$B$804,"Italiaonline",Registro!$A$5:$A$804,">="&DATE(2026,1,1)) -> 1 | C29: =COUNTIFS(Registro!$T$5:$T$804,$A29,Registro!$B$5:$B$804,"PgCasa (Italiaonline)",Registro!$A$5:$A$804,">="&DATE(2026,1,1)) -> 1 | D29: =COUNTIFS(Registro!$T$5:$T$804,$A29,Registro!$B$5:$B$804,"Internet",Registro!$A$5:$A$804,">="&DATE(2026,1,1)) -> 4 | E29: =COUNTIFS(Registro!$T$5:$T$804,$A29,Registro!$B$5:$B$804,"Passaparola",Registro!$A$5:$A$804,">="&DATE(2026,1,1)) -> 2 | F29: =G29-SUM(B29:E29) -> 0 | G29: =COUNTIFS(Registro!$T$5:$T$804,$A29,Registro!$A$5:$A$804,">="&DATE(2026,1,1)) -> 8 | H29: Bonifiche (3 su 8)
A30: Loano / Borghetto / Pietra | B30: =COUNTIFS(Registro!$T$5:$T$804,$A30,Registro!$B$5:$B$804,"Italiaonline",Registro!$A$5:$A$804,">="&DATE(2026,1,1)) -> 2 | C30: =COUNTIFS(Registro!$T$5:$T$804,$A30,Registro!$B$5:$B$804,"PgCasa (Italiaonline)",Registro!$A$5:$A$804,">="&DATE(2026,1,1)) -> 1 | D30: =COUNTIFS(Registro!$T$5:$T$804,$A30,Registro!$B$5:$B$804,"Internet",Registro!$A$5:$A$804,">="&DATE(2026,1,1)) -> 1 | E30: =COUNTIFS(Registro!$T$5:$T$804,$A30,Registro!$B$5:$B$804,"Passaparola",Registro!$A$5:$A$804,">="&DATE(2026,1,1)) -> 10 | F30: =G30-SUM(B30:E30) -> 2 | G30: =COUNTIFS(Registro!$T$5:$T$804,$A30,Registro!$A$5:$A$804,">="&DATE(2026,1,1)) -> 16 | H30: Disinfestazione (4 su 16)
A31: Albenga | B31: =COUNTIFS(Registro!$T$5:$T$804,$A31,Registro!$B$5:$B$804,"Italiaonline",Registro!$A$5:$A$804,">="&DATE(2026,1,1)) -> 1 | C31: =COUNTIFS(Registro!$T$5:$T$804,$A31,Registro!$B$5:$B$804,"PgCasa (Italiaonline)",Registro!$A$5:$A$804,">="&DATE(2026,1,1)) -> 0 | D31: =COUNTIFS(Registro!$T$5:$T$804,$A31,Registro!$B$5:$B$804,"Internet",Registro!$A$5:$A$804,">="&DATE(2026,1,1)) -> 0 | E31: =COUNTIFS(Registro!$T$5:$T$804,$A31,Registro!$B$5:$B$804,"Passaparola",Registro!$A$5:$A$804,">="&DATE(2026,1,1)) -> 3 | F31: =G31-SUM(B31:E31) -> 0 | G31: =COUNTIFS(Registro!$T$5:$T$804,$A31,Registro!$A$5:$A$804,">="&DATE(2026,1,1)) -> 4 | H31: Bonifiche (2 su 4)
A32: Genova | B32: =COUNTIFS(Registro!$T$5:$T$804,$A32,Registro!$B$5:$B$804,"Italiaonline",Registro!$A$5:$A$804,">="&DATE(2026,1,1)) -> 0 | C32: =COUNTIFS(Registro!$T$5:$T$804,$A32,Registro!$B$5:$B$804,"PgCasa (Italiaonline)",Registro!$A$5:$A$804,">="&DATE(2026,1,1)) -> 0 | D32: =COUNTIFS(Registro!$T$5:$T$804,$A32,Registro!$B$5:$B$804,"Internet",Registro!$A$5:$A$804,">="&DATE(2026,1,1)) -> 3 | E32: =COUNTIFS(Registro!$T$5:$T$804,$A32,Registro!$B$5:$B$804,"Passaparola",Registro!$A$5:$A$804,">="&DATE(2026,1,1)) -> 3 | F32: =G32-SUM(B32:E32) -> 1 | G32: =COUNTIFS(Registro!$T$5:$T$804,$A32,Registro!$A$5:$A$804,">="&DATE(2026,1,1)) -> 7 | H32: Da Specificare (5 su 7)
A33: Cisano (V.A.L.) | B33: =COUNTIFS(Registro!$T$5:$T$804,$A33,Registro!$B$5:$B$804,"Italiaonline",Registro!$A$5:$A$804,">="&DATE(2026,1,1)) -> 0 | C33: =COUNTIFS(Registro!$T$5:$T$804,$A33,Registro!$B$5:$B$804,"PgCasa (Italiaonline)",Registro!$A$5:$A$804,">="&DATE(2026,1,1)) -> 0 | D33: =COUNTIFS(Registro!$T$5:$T$804,$A33,Registro!$B$5:$B$804,"Internet",Registro!$A$5:$A$804,">="&DATE(2026,1,1)) -> 0 | E33: =COUNTIFS(Registro!$T$5:$T$804,$A33,Registro!$B$5:$B$804,"Passaparola",Registro!$A$5:$A$804,">="&DATE(2026,1,1)) -> 0 | F33: =G33-SUM(B33:E33) -> 0 | G33: =COUNTIFS(Registro!$T$5:$T$804,$A33,Registro!$A$5:$A$804,">="&DATE(2026,1,1)) -> 0 | H33: —
A34: Zone senza striscioni/cartelloni | B34: =COUNTIFS(Registro!$T$5:$T$804,$A34,Registro!$B$5:$B$804,"Italiaonline",Registro!$A$5:$A$804,">="&DATE(2026,1,1)) -> 32 | C34: =COUNTIFS(Registro!$T$5:$T$804,$A34,Registro!$B$5:$B$804,"PgCasa (Italiaonline)",Registro!$A$5:$A$804,">="&DATE(2026,1,1)) -> 6 | D34: =COUNTIFS(Registro!$T$5:$T$804,$A34,Registro!$B$5:$B$804,"Internet",Registro!$A$5:$A$804,">="&DATE(2026,1,1)) -> 29 | E34: =COUNTIFS(Registro!$T$5:$T$804,$A34,Registro!$B$5:$B$804,"Passaparola",Registro!$A$5:$A$804,">="&DATE(2026,1,1)) -> 58 | F34: =G34-SUM(B34:E34) -> 5 | G34: =COUNTIFS(Registro!$T$5:$T$804,$A34,Registro!$A$5:$A$804,">="&DATE(2026,1,1)) -> 130 | H34: Rifiuti (33 su 130)
A36: CONCLUSIONE
A37: 1) Nel registro chiamate 2026 NESSUN contatto è segnato come arrivato da striscione o cartellone: la reception non ha questa voce in 'Provenienza'.
A38: 2) Dalle zone con striscioni (Sanremo-Taggia, Imperia, Loano-Borghetto-Pietra, Albenga) arrivano chiamate, ma quasi tutte dichiarate 'Passaparola', 'Italiaonline' o 'Internet'.
A39: 3) Genova (2 cartelloni CIBRA, circa 2.185 €/anno): 7 chiamate, 3 dal sito e 3 da passaparola, nessuna dal cartellone.
A40: 4) Da fare subito: aggiungere in reception la provenienza 'STRISCIONE/CARTELLONE' + chiedere sempre 'dove ci ha visto?'. Senza questo dato non si può misurare il ritorno degli striscioni.
A41: 5) Prima di firmare Pontelungo (5.000 € in 3 anni) conviene 3 mesi di prova con la domanda in reception.

Sheet Rubriche web
A1: Contatti dal modulo web (rubriche Italiaonline) – confronto con il Registro
A2: File: rubrica Contatti sito dal 2021, Rubrica IOL al 29/10/2025, Backup rubrica 17/08/2026. 'Nel registro?' si aggiorna da solo cercando l'email nel Registro
A4: Data | B4: Mese | C4: Rubrica | D4: Nome | E4: Cognome | F4: Telefono (dal CSV) | G4: Email | H4: Newsletter | I4: Nel registro? | K4: Riepilogo per anno | L4: Contatti web | M4: Media al mese
A5: 46230 | B5: =TEXT(A5,"yyyy-mm") -> 2026-07 | C5: IOL 2026 | D5: SIMONE | E5: CONTI | F5: 3,93355E+11 | G5: simonecontig@gmail.com | H5: no | I5: =IF(G5="","",IF(COUNTIF(Registro!$G$5:$G$804,G5)>0,"SI","NO")) -> NO | K5: 2021 (da apr) | L5: =COUNTIFS($A$5:$A$293,">="&DATE(2021,1,1),$A$5:$A$293,"<"&DATE(2022,1,1)) -> 13 | M5: =L5/9 -> 1.4444444
A6: 46219 | B6: =TEXT(A6,"yyyy-mm") -> 2026-07 | C6: IOL 2026 | D6: Alessandro | E6: Averla | F6: 3,90198E+11 | G6: info@averla.it | H6: sì | I6: =IF(G6="","",IF(COUNTIF(Registro!$G$5:$G$804,G6)>0,"SI","NO")) -> SI | K6: 2022 | L6: =COUNTIFS($A$5:$A$293,">="&DATE(2022,1,1),$A$5:$A$293,"<"&DATE(2023,1,1)) -> 24 | M6: =L6/12 -> 2
A7: 46205 | B7: =TEXT(A7,"yyyy-mm") -> 2026-07 | C7: IOL 2026 | D7: Monica | E7: Molecca | F7: 3,93477E+11 | G7: monicavale1972@libero.it | H7: no | I7: =IF(G7="","",IF(COUNTIF(Registro!$G$5:$G$804,G7)>0,"SI","NO")) -> NO | K7: 2023 | L7: =COUNTIFS($A$5:$A$293,">="&DATE(2023,1,1),$A$5:$A$293,"<"&DATE(2024,1,1)) -> 23 | M7: =L7/12 -> 1.9166667
A8: 46190 | B8: =TEXT(A8,"yyyy-mm") -> 2026-06 | C8: IOL 2026 | D8: INOX | E8: SIGNAL | F8: 39019801737 | G8: inoxsignalsrl@gmail.com | H8: sì | I8: =IF(G8="","",IF(COUNTIF(Registro!$G$5:$G$804,G8)>0,"SI","NO")) -> NO | K8: 2024 | L8: =COUNTIFS($A$5:$A$293,">="&DATE(2024,1,1),$A$5:$A$293,"<"&DATE(2025,1,1)) -> 78 | M8: =L8/12 -> 6.5
A9: 46187 | B9: =TEXT(A9,"yyyy-mm") -> 2026-06 | C9: IOL 2026 | D9: umberto | E9: di sario | F9: 3,93277E+11 | G9: desse10@virgilio.it | H9: sì | I9: =IF(G9="","",IF(COUNTIF(Registro!$G$5:$G$804,G9)>0,"SI","NO")) -> NO | K9: 2025 (fino a ott) | L9: =COUNTIFS($A$5:$A$293,">="&DATE(2025,1,1),$A$5:$A$293,"<"&DATE(2026,1,1)) -> 121 | M9: =L9/10 -> 12.1
A10: 46178 | B10: =TEXT(A10,"yyyy-mm") -> 2026-06 | C10: IOL 2026 | D10: Stefan | E10: Politzka | F10: 4,91793E+11 | G10: stefan_politzka@posteo.de | H10: no | I10: =IF(G10="","",IF(COUNTIF(Registro!$G$5:$G$804,G10)>0,"SI","NO")) -> NO | K10: 2026 (mar–lug) | L10: =COUNTIFS($A$5:$A$293,">="&DATE(2026,1,1),$A$5:$A$293,"<"&DATE(2027,1,1)) -> 30 | M10: =L10/5 -> 6
A11: 46171 | B11: =TEXT(A11,"yyyy-mm") -> 2026-05 | C11: IOL 2026 | D11: Chiara | E11: Orlandini | F11: 3,93665E+11 | G11: chiara.or.999@gmail.com | H11: no | I11: =IF(G11="","",IF(COUNTIF(Registro!$G$5:$G$804,G11)>0,"SI","NO")) -> NO
A12: 46171 | B12: =TEXT(A12,"yyyy-mm") -> 2026-05 | C12: IOL 2026 | D12: Stefania | E12: Pisano | F12: 3,93342E+11 | G12: ste.pi72@yahoo.it | H12: sì | I12: =IF(G12="","",IF(COUNTIF(Registro!$G$5:$G$804,G12)>0,"SI","NO")) -> NO | K12: Contatti web 2026 | L12: =COUNTIFS($A$5:$A$293,">="&DATE(2026,1,1)) -> 30
A13: 46170 | B13: =TEXT(A13,"yyyy-mm") -> 2026-05 | C13: IOL 2026 | D13: ChangHong | E13: S.R.L | F13: 3,93384E+11 | G13: chdstudio2026@gmail.com | H13: no | I13: =IF(G13="","",IF(COUNTIF(Registro!$G$5:$G$804,G13)>0,"SI","NO")) -> NO | K13: …di cui presenti nel Registro | L13: =COUNTIFS($A$5:$A$293,">="&DATE(2026,1,1),$I$5:$I$293,"SI") -> 13
A14: 46168 | B14: =TEXT(A14,"yyyy-mm") -> 2026-05 | C14: IOL 2026 | D14: Giovanni | E14: Denert | F14: 3,93467E+11 | G14: giovanni.denert@gmail.com | H14: no | I14: =IF(G14="","",IF(COUNTIF(Registro!$G$5:$G$804,G14)>0,"SI","NO")) -> NO | K14: …NON presenti nel Registro | L14: =L12-L13 -> 17
A15: 46155 | B15: =TEXT(A15,"yyyy-mm") -> 2026-05 | C15: IOL 2026 | D15: Alessandra | E15: Minelli | F15: 3,93409E+11 | G15: minelli.amministrazioni@gmail.com | H15: no | I15: =IF(G15="","",IF(COUNTIF(Registro!$G$5:$G$804,G15)>0,"SI","NO")) -> NO
A16: 46152 | B16: =TEXT(A16,"yyyy-mm") -> 2026-05 | C16: IOL 2026 | D16: Alessandro | E16: Para | F16: 3,93478E+11 | G16: para.alessandro@libero.it | H16: no | I16: =IF(G16="","",IF(COUNTIF(Registro!$G$5:$G$804,G16)>0,"SI","NO")) -> SI | K16: Nota: i CSV hanno i telefoni in formato scientifico (es. 3,93385E+11): cifre perse. Esportare di nuovo dall'area clienti Italiaonline aprendo il CSV come testo.
A17: 46149 | B17: =TEXT(A17,"yyyy-mm") -> 2026-05 | C17: IOL 2026 | D17: Adriana | E17: Popolo | F17: 3,93385E+11 | G17: adrianapopolo02@gmail.com | H17: no | I17: =IF(G17="","",IF(COUNTIF(Registro!$G$5:$G$804,G17)>0,"SI","NO")) -> SI | K17: Manca il periodo nov 2025 – feb 2026 (nessuna rubrica esportata).
A18: 46145 | B18: =TEXT(A18,"yyyy-mm") -> 2026-05 | C18: IOL 2026 | D18: Ireni | E18: Oliveira | F18: 3,9327E+11 | G18: irenibarbosa.ib@gmail.com | H18: sì | I18: =IF(G18="","",IF(COUNTIF(Registro!$G$5:$G$804,G18)>0,"SI","NO")) -> NO
A19: 46139 | B19: =TEXT(A19,"yyyy-mm") -> 2026-04 | C19: IOL 2026 | D19: Andrea | E19: Magni | F19: 3,93356E+11 | G19: andreamagni@me.com | H19: no | I19: =IF(G19="","",IF(COUNTIF(Registro!$G$5:$G$804,G19)>0,"SI","NO")) -> NO
A20: 46137 | B20: =TEXT(A20,"yyyy-mm") -> 2026-04 | C20: IOL 2026 | D20: ELDA | E20: CARAGNO | F20: 3,93394E+11 | G20: cfcarni@libero.it | H20: sì | I20: =IF(G20="","",IF(COUNTIF(Registro!$G$5:$G$804,G20)>0,"SI","NO")) -> NO
A21: 46137 | B21: =TEXT(A21,"yyyy-mm") -> 2026-04 | C21: IOL 2026 | D21: roberto | E21: locatelli | F21: 3,93386E+11 | G21: robiloca68@gmail.com | H21: sì | I21: =IF(G21="","",IF(COUNTIF(Registro!$G$5:$G$804,G21)>0,"SI","NO")) -> NO
A22: 46136 | B22: =TEXT(A22,"yyyy-mm") -> 2026-04 | C22: IOL 2026 | D22: Martin | E22: Nilsson | F22: 46768653193 | G22: martin.nilsson7210@gmail.com.com | H22: no | I22: =IF(G22="","",IF(COUNTIF(Registro!$G$5:$G$804,G22)>0,"SI","NO")) -> NO
A23: 46135 | B23: =TEXT(A23,"yyyy-mm") -> 2026-04 | C23: IOL 2026 | D23: Fulvio Francesco | E23: Palmieri | F23: 3,93487E+11 | G23: fulvioingpalmieri@libero.it | H23: sì | I23: =IF(G23="","",IF(COUNTIF(Registro!$G$5:$G$804,G23)>0,"SI","NO")) -> NO
A24: 46134 | B24: =TEXT(A24,"yyyy-mm") -> 2026-04 | C24: IOL 2026 | D24: Emily | E24: Mirch | F24: 39347369777 | G24: mirchemily@gmail.com | H24: sì | I24: =IF(G24="","",IF(COUNTIF(Registro!$G$5:$G$804,G24)>0,"SI","NO")) -> SI
A25: 46134 | B25: =TEXT(A25,"yyyy-mm") -> 2026-04 | C25: IOL 2026 | D25: Ettore | E25: Carpentieri | F25: 3,93406E+11 | G25: ettore.carpentieri@gmail.com | H25: no | I25: =IF(G25="","",IF(COUNTIF(Registro!$G$5:$G$804,G25)>0,"SI","NO")) -> SI
A26: 46133 | B26: =TEXT(A26,"yyyy-mm") -> 2026-04 | C26: IOL 2026 | D26: Lucrezia | E26: Fasolo | F26: 3,93202E+11 | G26: lucreziafasolo94@gmail.com | H26: sì | I26: =IF(G26="","",IF(COUNTIF(Registro!$G$5:$G$804,G26)>0,"SI","NO")) -> SI
A27: 46132 | B27: =TEXT(A27,"yyyy-mm") -> 2026-04 | C27: IOL 2026 | D27: Anna | E27: Marangon | F27: 3,93287E+11 | G27: maria.m48@icloud.com | H27: no | I27: =IF(G27="","",IF(COUNTIF(Registro!$G$5:$G$804,G27)>0,"SI","NO")) -> SI
A28: 46132 | B28: =TEXT(A28,"yyyy-mm") -> 2026-04 | C28: IOL 2026 | D28: Felisia | E28: D’Andrea | F28: 3,93407E+11 | G28: felisiadandrea@libero.it | H28: no | I28: =IF(G28="","",IF(COUNTIF(Registro!$G$5:$G$804,G28)>0,"SI","NO")) -> SI
A29: 46127 | B29: =TEXT(A29,"yyyy-mm") -> 2026-04 | C29: IOL 2026 | D29: Riccardo | E29: Campi | F29: 3,93495E+11 | G29: rikic1979@gmail.com | H29: no | I29: =IF(G29="","",IF(COUNTIF(Registro!$G$5:$G$804,G29)>0,"SI","NO")) -> NO
... A293: 44316 | B293: =TEXT(A293,"yyyy-mm") -> 2021-04 | C293: Sito 2021-2024 | D293: anna | E293: cusati | F293: 3901995488 | G293: info@residencelavignetta.it | H293: no | I293: =IF(G293="","",IF(COUNTIF(Registro!$G$5:$G$804,G293)>0,"SI","NO")) -> NO

Sheet Bilancio e servizi
A1: Ricavi per servizio 2023-2025 (bilancio) e richieste 2026 (registro)
A2: Fonte: Bilancio comparato Servizi Ecologici 23-24-25, conti 58/05/xxx. Contatti 2026 = righe del Registro per area/servizio
A4: Voce di ricavo (bilancio) | B4: 2023 € | C4: 2024 € | D4: 2025 € | E4: Var. 2025 su 2024 | F4: Area | G4: Contatti 2026 nel registro (area)
A5: Disostruzione canaljet reti/fosse | B5: 772916.86 | C5: 929156.23 | D5: 792167.46 | E5: =IFERROR(D5/C5-1,"") -> -0.14743352 | F5: SPURGHI E RETI | G5: =COUNTIFS(Registro!$J$5:$J$804,F5,Registro!$A$5:$A$804,">="&DATE(2026,1,1)) -> 28
A6: Ispezioni televisive | B6: 58293.86 | C6: 57215.81 | D6: 44209.63 | E6: =IFERROR(D6/C6-1,"") -> -0.22731794 | F6: SPURGHI E RETI | G6: =COUNTIFS(Registro!$J$5:$J$804,F6,Registro!$A$5:$A$804,">="&DATE(2026,1,1)) -> 28
A7: Posizionamento e ritiro cassoni | B7: 451265.44 | C7: 281562.02 | D7: 332478.44 | E7: =IFERROR(D7/C7-1,"") -> 0.18083554 | F7: RIFIUTI | G7: =COUNTIFS(Registro!$J$5:$J$804,F7,Registro!$A$5:$A$804,">="&DATE(2026,1,1)) -> 38
A8: Smaltimento rifiuti liquidi | B8: 315159.57 | C8: 242199.58 | D8: 213118.59 | E8: =IFERROR(D8/C8-1,"") -> -0.12007036 | F8: RIFIUTI | G8: =COUNTIFS(Registro!$J$5:$J$804,F8,Registro!$A$5:$A$804,">="&DATE(2026,1,1)) -> 38
A9: Smaltimento rifiuti solidi | B9: 315000.33 | C9: 225097.09 | D9: 207869.67 | E9: =IFERROR(D9/C9-1,"") -> -0.076533286 | F9: RIFIUTI | G9: =COUNTIFS(Registro!$J$5:$J$804,F9,Registro!$A$5:$A$804,">="&DATE(2026,1,1)) -> 38
A10: Smaltimento inerti | B10: 319556.84 | C10: 43442.59 | D10: 59058.42 | E10: =IFERROR(D10/C10-1,"") -> 0.359459 | F10: RIFIUTI | G10: =COUNTIFS(Registro!$J$5:$J$804,F10,Registro!$A$5:$A$804,">="&DATE(2026,1,1)) -> 38
A11: Analisi rifiuti solidi e liquidi | B11: 22135 | C11: 26370 | D11: 31140 | E11: =IFERROR(D11/C11-1,"") -> 0.18088737 | F11: DA SPECIFICARE | G11: =COUNTIFS(Registro!$J$5:$J$804,F11,Registro!$A$5:$A$804,">="&DATE(2026,1,1)) -> 31
A12: Analisi, smaltimento e incapsulamento amianto | B12: 383945.8 | C12: 342170.88 | D12: 228926.1 | E12: =IFERROR(D12/C12-1,"") -> -0.33095972 | F12: BONIFICHE | G12: =COUNTIFS(Registro!$J$5:$J$804,F12,Registro!$A$5:$A$804,">="&DATE(2026,1,1)) -> 38
A13: Censimento amianto | B13: 8540 | C13: 1280 | D13: 48202.8 | E13: =IFERROR(D13/C13-1,"") -> 36.658437 | F13: BONIFICHE | G13: =COUNTIFS(Registro!$J$5:$J$804,F13,Registro!$A$5:$A$804,">="&DATE(2026,1,1)) -> 38
A14: Analisi amianto | B14: 11180 | C14: 7650 | D14: 1460 | E14: =IFERROR(D14/C14-1,"") -> -0.80915033 | F14: BONIFICHE | G14: =COUNTIFS(Registro!$J$5:$J$804,F14,Registro!$A$5:$A$804,">="&DATE(2026,1,1)) -> 38
A15: Bonifiche ambientali | B15: 39634 | C15: 295400.25 | D15: 94274.44 | E15: =IFERROR(D15/C15-1,"") -> -0.68085863 | F15: BONIFICHE | G15: =COUNTIFS(Registro!$J$5:$J$804,F15,Registro!$A$5:$A$804,">="&DATE(2026,1,1)) -> 38
A16: Disinfestazioni e derattizzazioni | B16: 139478.33 | C16: 126183.27 | D16: 140242.37 | E16: =IFERROR(D16/C16-1,"") -> 0.1114181 | F16: DISINFESTAZIONE | G16: =COUNTIFS(Registro!$J$5:$J$804,F16,Registro!$A$5:$A$804,">="&DATE(2026,1,1)) -> 30
... A21: Noleggio bagni chimici | B21: 51093.4 | C21: 34597.36 | D21: 1450 | E21: =IFERROR(D21/C21-1,"") -> -0.95808929 | F21: SPURGHI E RETI | G21: =COUNTIFS(Registro!$J$5:$J$804,F21,Registro!$A$5:$A$804,">="&DATE(2026,1,1)) -> 28
A22: Vendite diverse / altro | B22: 102304.28 | C22: 64663.71 | D22: 76329.29 | E22: =IFERROR(D22/C22-1,"") -> 0.18040382
A23: TOTALE ricavi delle vendite (bilancio) | B23: 3030649.5 | C23: 2721837.2 | D23: 2340723.8 | E23: =D23/C23-1 -> -0.14002065
A24: Somma righe sopra (controllo) | B24: =SUM(B5:B22) -> 3030649.5 | C24: =SUM(C5:C22) -> 2721837.2 | D24: =SUM(D5:D22) -> 2340723.8
A25: Utile d'esercizio | B25: 56275.46 | C25: 86005 | D25: 2075.89
A28: Richieste 2026 per area (registro) vs ricavi 2025
A29: Area | B29: Ricavi 2025 € (voci sopra) | C29: Contatti 2026 | D29: di cui Italiaonline + PgCasa
A30: SPURGHI E RETI | B30: =SUMIF($F$5:$F$22,A30,$D$5:$D$22) -> 837827.09 | C30: =COUNTIFS(Registro!$J$5:$J$804,A30,Registro!$A$5:$A$804,">="&DATE(2026,1,1)) -> 28 | D30: =COUNTIFS(Registro!$J$5:$J$804,A30,Registro!$B$5:$B$804,"Italiaonline",Registro!$A$5:$A$804,">="&DATE(2026,1,1))+COUNTIFS(Registro!$J$5:$J$804,A30,Registro!$B$5:$B$804,"PgCasa (Italiaonline)",Registro!$A$5:$A$804,">="&DATE(2026,1,1)) -> 10
A31: RIFIUTI | B31: =SUMIF($F$5:$F$22,A31,$D$5:$D$22) -> 812525.12 | C31: =COUNTIFS(Registro!$J$5:$J$804,A31,Registro!$A$5:$A$804,">="&DATE(2026,1,1)) -> 38 | D31: =COUNTIFS(Registro!$J$5:$J$804,A31,Registro!$B$5:$B$804,"Italiaonline",Registro!$A$5:$A$804,">="&DATE(2026,1,1))+COUNTIFS(Registro!$J$5:$J$804,A31,Registro!$B$5:$B$804,"PgCasa (Italiaonline)",Registro!$A$5:$A$804,">="&DATE(2026,1,1)) -> 8
A32: BONIFICHE | B32: =SUMIF($F$5:$F$22,A32,$D$5:$D$22) -> 372863.34 | C32: =COUNTIFS(Registro!$J$5:$J$804,A32,Registro!$A$5:$A$804,">="&DATE(2026,1,1)) -> 38 | D32: =COUNTIFS(Registro!$J$5:$J$804,A32,Registro!$B$5:$B$804,"Italiaonline",Registro!$A$5:$A$804,">="&DATE(2026,1,1))+COUNTIFS(Registro!$J$5:$J$804,A32,Registro!$B$5:$B$804,"PgCasa (Italiaonline)",Registro!$A$5:$A$804,">="&DATE(2026,1,1)) -> 10
A33: DISINFESTAZIONE | B33: =SUMIF($F$5:$F$22,A33,$D$5:$D$22) -> 140242.37 | C33: =COUNTIFS(Registro!$J$5:$J$804,A33,Registro!$A$5:$A$804,">="&DATE(2026,1,1)) -> 30 | D33: =COUNTIFS(Registro!$J$5:$J$804,A33,Registro!$B$5:$B$804,"Italiaonline",Registro!$A$5:$A$804,">="&DATE(2026,1,1))+COUNTIFS(Registro!$J$5:$J$804,A33,Registro!$B$5:$B$804,"PgCasa (Italiaonline)",Registro!$A$5:$A$804,">="&DATE(2026,1,1)) -> 9
A34: IGIENE IMPIANTI | B34: =SUMIF($F$5:$F$22,A34,$D$5:$D$22) -> 13540 | C34: =COUNTIFS(Registro!$J$5:$J$804,A34,Registro!$A$5:$A$804,">="&DATE(2026,1,1)) -> 14 | D34: =COUNTIFS(Registro!$J$5:$J$804,A34,Registro!$B$5:$B$804,"Italiaonline",Registro!$A$5:$A$804,">="&DATE(2026,1,1))+COUNTIFS(Registro!$J$5:$J$804,A34,Registro!$B$5:$B$804,"PgCasa (Italiaonline)",Registro!$A$5:$A$804,">="&DATE(2026,1,1)) -> 7
A35: DA SPECIFICARE | B35: =SUMIF($F$5:$F$22,A35,$D$5:$D$22) -> 87396.56 | C35: =COUNTIFS(Registro!$J$5:$J$804,A35,Registro!$A$5:$A$804,">="&DATE(2026,1,1)) -> 31 | D35: =COUNTIFS(Registro!$J$5:$J$804,A35,Registro!$B$5:$B$804,"Italiaonline",Registro!$A$5:$A$804,">="&DATE(2026,1,1))+COUNTIFS(Registro!$J$5:$J$804,A35,Registro!$B$5:$B$804,"PgCasa (Italiaonline)",Registro!$A$5:$A$804,">="&DATE(2026,1,1)) -> 7

Sheet Registro
A1: Registro contatti e lavori
A2: 184 contatti caricati (168 dal registro chiamate 2026 + 16 PgCasa). Celle gialle da compilare: ESITO e MOTIVO servono per le statistiche
A4: Data | B4: Fonte | C4: Dettaglio fonte | D4: Cliente | E4: Tipo cliente | F4: Telefono | G4: Email | H4: Comune | I4: Prov. | J4: Area servizio | K4: Servizio (dal foglio Servizi) | L4: Richiesta del cliente | M4: Esito | N4: Motivo (se NON PRESO) | O4: Importo preventivo € | P4: Importo lavoro fatto € | Q4: Costo contatto € | R4: Commerciale (cod.) | S4: Note | T4: Zona pubblicità locale
A5: 44823 | B5: PgCasa (Italiaonline) | C5: Richiesta preventivo PgCasa | D5: Alessandro F. | E5: Privato | F5: 3488121357 | G5: aferraro720@gmail.com | H5: Loano | I5: SV | J5: DISINFESTAZIONE | K5: Allontanamento volatili (piccioni, gabbiani) | L5: Allontanamento piccioni/volatili | M5: DA RICONTATTARE | Q5: 5 | S5: esito da verificare | T5: Loano / Borghetto / Pietra
A6: 45187 | B6: PgCasa (Italiaonline) | C6: Richiesta preventivo PgCasa | D6: Giancarlo R. | E6: Privato | F6: 3428016129 | G6: acovasco@yahoo.it | H6: Tovo San Giacomo | I6: SV | J6: SPURGHI E RETI | K6: Canaljet – autospurgo fosse biologiche, fognature, pozzetti, degrassatori | L6: Spurgo tubo acque bianche | M6: DA RICONTATTARE | Q6: 5 | S6: esito da verificare | T6: Zone senza striscioni/cartelloni
A7: 45187 | B7: PgCasa (Italiaonline) | C7: Richiesta preventivo PgCasa | D7: Andrea Z. | E7: Privato | F7: 3313761023 | G7: andrea.zannoli@gmail.com | H7: Camporosso | I7: IM | J7: SPURGHI E RETI | K7: Canaljet – autospurgo fosse biologiche, fognature, pozzetti, degrassatori | L7: Spurgo fossa settica: Fossa settica casa indipendente ~6000 l | M7: DA RICONTATTARE | Q7: 5 | S7: esito da verificare | T7: Zone senza striscioni/cartelloni
A8: 45187 | B8: PgCasa (Italiaonline) | C8: Richiesta preventivo PgCasa | D8: Silvana S. | E8: Azienda / Società | F8: 3356698662 | G8: info@nattadimontetabor.it | H8: Celle Ligure | I8: SV | J8: DISINFESTAZIONE | K8: Derattizzazione, disinfestazione insetti, disinfezione, sanificazione | L8: Derattizzazione | M8: DA RICONTATTARE | Q8: 5 | S8: esito da verificare | T8: Zone senza striscioni/cartelloni
A9: 45224 | B9: PgCasa (Italiaonline) | C9: Richiesta preventivo PgCasa | D9: Valentina B. | E9: Privato | F9: 3466961758 | G9: valentina.bach@uwcad.it | H9: Albisola Superiore | I9: SV | J9: DISINFESTAZIONE | K9: Derattizzazione, disinfestazione insetti, disinfezione, sanificazione | L9: Derattizzazione: Verifica e interventi senza veleno | M9: DA RICONTATTARE | Q9: 5 | S9: esito da verificare | T9: Zone senza striscioni/cartelloni
A10: 46029 | B10: Italiaonline | D10: Tortarolo Guglielmo | E10: Attività / Turismo | F10: 3663699474 | G10: guglielmo@hotel-sanmichele.it | H10: Celle Ligure | I10: SV | J10: IGIENE IMPIANTI | K10: Pulizia canne fumarie (spazzacamino) | L10: Ispezione TV canne fumarie | M10: DA VERIFICARE | R10: 1 | S10: Registro chiamate 2026 – motivo 'IT CANNE' – tipologia 'Attività' – esito da inserire | T10: Zone senza striscioni/cartelloni
A11: 46030 | B11: Italiaonline | D11: Raffaele Corrado | E11: Privato | F11: 3470732628 | G11: crrrfl93a20@gmail.com | H11: Finale Ligure | I11: SV | J11: IGIENE IMPIANTI | K11: Pulizia canne fumarie (spazzacamino) | L11: Ispezione TV canne fumarie | M11: DA VERIFICARE | R11: 34 | S11: Registro chiamate 2026 – motivo 'IT CANNE' – tipologia 'Privato' – esito da inserire | T11: Zone senza striscioni/cartelloni
A12: 46030 | B12: Italiaonline | D12: Furlanetto Davide | E12: Privato | F12: 3397972961 | G12: geom.davidefurla@libero.it | H12: Andora | I12: SV | J12: BONIFICHE | K12: Rimozione e smaltimento amianto – eternit | L12: Amianto | M12: DA VERIFICARE | R12: 11 | S12: Registro chiamate 2026 – motivo 'AMIANTO' – tipologia 'Privato' – esito da inserire | T12: Zone senza striscioni/cartelloni
A13: 46030 | B13: Italiaonline | D13: D'Aquino Mario | E13: Privato | F13: 3357352754 | G13: bymario@libero.it | H13: Albisola Marina | I13: SV | J13: IGIENE IMPIANTI | K13: Pulizia canne fumarie (spazzacamino) | L13: Ispezione TV canne fumarie | M13: DA VERIFICARE | R13: 4 | S13: Registro chiamate 2026 – motivo 'IT CANNE' – tipologia 'Privato' – esito da inserire | T13: Zone senza striscioni/cartelloni
A14: 46033 | B14: Internet | C14: Nostro Sito | D14: Garzino Alberto | E14: Impresa edile / Artigiano | F14: 3391218326 | G14: alberto.garzino@virgilio.it | H14: Spotorno | I14: SV | J14: RIFIUTI | K14: Smaltimento rifiuti pericolosi e non pericolosi | L14: Rifiuti | M14: DA VERIFICARE | R14: 4 | S14: Registro chiamate 2026 – motivo 'RIFIUTI' – tipologia 'Imp. Edile' – esito da inserire | T14: Zone senza striscioni/cartelloni
A15: 46037 | B15: Italiaonline | D15: Domenico Timpano | E15: Privato | F15: 3401426500 | G15: domytim31@gmail.com | H15: Borgio Verezzi | I15: SV | J15: RIFIUTI | K15: Smaltimento rifiuti pericolosi e non pericolosi | L15: Rifiuti | M15: DA VERIFICARE | R15: 4 | S15: Registro chiamate 2026 – motivo 'RIFIUTI' – tipologia 'Privato' – esito da inserire | T15: Zone senza striscioni/cartelloni
A16: 46037 | B16: Italiaonline | D16: Roberto Parodi | E16: Privato | F16: 3929973357 | G16: info@studioparodi.org | H16: Savona | I16: SV | J16: RIFIUTI | K16: Smaltimento rifiuti pericolosi e non pericolosi | L16: Rifiuti | M16: DA VERIFICARE | R16: 4 | S16: Registro chiamate 2026 – motivo 'RIFIUTI' – tipologia 'Privato' – esito da inserire | T16: Zone senza striscioni/cartelloni
A17: 46038 | B17: Internet | C17: Nostro Sito | D17: Melina Alice | E17: Privato | F17: 3470865194 | G17: alice.melina@tim.it | H17: Imperia | I17: IM | J17: BONIFICHE | K17: Rimozione e smaltimento amianto – eternit | L17: Amianto | M17: DA VERIFICARE | R17: 11 | S17: Registro chiamate 2026 – motivo 'AMIANTO' – tipologia 'Privato' – esito da inserire | T17: Imperia
A18: 46041 | B18: Internet | C18: Nostro Sito | D18: Expertise Srl | E18: Azienda / Società | F18: 3498225725 | G18: federica.alesiani@expertise.it | H18: Vado Ligure | I18: SV | J18: DISINFESTAZIONE | K18: Derattizzazione, disinfestazione insetti, disinfezione, sanificazione | L18: Sanificazione | M18: DA VERIFICARE | R18: 4 | S18: Registro chiamate 2026 – motivo 'SANIFICAZI' – tipologia 'Associazione' – esito da inserire | T18: Zone senza striscioni/cartelloni
A19: 46045 | B19: Internet | C19: Nostro Sito | D19: Global Psa | E19: Azienda / Società | F19: 3315718808 | G19: alessandra.raffaele@globalpsa. | H19: Genova | I19: GE | J19: DA SPECIFICARE | L19: Pulizia (specificare: cisterne, facciate, cappe…) | M19: DA VERIFICARE | R19: 34 | S19: Registro chiamate 2026 – motivo 'PULIZ.' – tipologia 'Manutentore' – esito da inserire | T19: Genova
A20: 46045 | B20: Internet | C20: Nostro Sito | D20: Cgg Spa | E20: Impresa edile / Artigiano | F20: 3351835165 | G20: zagarese@gilardi.it | H20: Genova | I20: GE | J20: BONIFICHE | K20: Bonifiche ambientali e discariche abusive | L20: Bonifica | M20: DA VERIFICARE | R20: 34 | S20: Registro chiamate 2026 – motivo 'BONIFICA' – tipologia 'Imp. Edile' – esito da inserire | T20: Genova
A21: 46048 | B21: Italiaonline | D21: Fantini Orazio | E21: Privato | F21: 3471172348 | G21: oraziofan73@gmail.com | H21: Pietra Ligure | I21: SV | J21: DA SPECIFICARE | L21: Analisi (specificare: acque potabili o rifiuti) | M21: DA VERIFICARE | R21: 34 | S21: Registro chiamate 2026 – motivo 'ANALISI' – tipologia 'Privato' – esito da inserire | T21: Loano / Borghetto / Pietra
A22: 46048 | B22: Internet | C22: Nostro Sito | D22: La Giglio Eco Group | E22: Impresa edile / Artigiano | F22: 055414559 | G22: cantieri@giglioecogroup.it | H22: Imperia | I22: IM | J22: BONIFICHE | K22: Rimozione e smaltimento amianto – eternit | L22: Amianto | M22: DA VERIFICARE | R22: 11 | S22: Registro chiamate 2026 – motivo 'AMIANTO' – tipologia 'Imp. Edile' – esito da inserire | T22: Imperia
A23: 46049 | B23: Passaparola | D23: Selvaggi Valerio | E23: Privato | F23: 3402836170 | H23: Cipressa | I23: IM | J23: BONIFICHE | K23: Rimozione e smaltimento amianto – eternit | L23: Amianto | M23: DA VERIFICARE | R23: 11 | S23: Registro chiamate 2026 – motivo 'AMIANTO' – tipologia 'Privato' – esito da inserire | T23: Zone senza striscioni/cartelloni
A24: 46051 | B24: Italiaonline | D24: Rossi Elide | E24: Privato | F24: 3280343380 | G24: rossi_elide@yahoo.com | H24: Xxmiglia | I24: IM | J24: BONIFICHE | K24: Rimozione e smaltimento amianto – eternit | L24: Amianto | M24: DA VERIFICARE | R24: 11 | S24: Registro chiamate 2026 – motivo 'AMIANTO' – tipologia 'Privato' – esito da inserire | T24: Zone senza striscioni/cartelloni
A25: 46054 | B25: PgCasa (Italiaonline) | C25: Richiesta preventivo PgCasa | D25: Fabio L. | E25: Privato | F25: 3911030392 | G25: f.leanzi@gmail.com | H25: Perinaldo | I25: IM | J25: SPURGHI E RETI | K25: Canaljet – autospurgo fosse biologiche, fognature, pozzetti, degrassatori | L25: Svuotamento fossa biologica: Fossa ~2 mq, serve camion piccolo (accesso stretto) | M25: DA RICONTATTARE | Q25: 10 | S25: Risposto 01/02 (Contini) – esito da verificare | T25: Zone senza striscioni/cartelloni
A26: 46056 | B26: Internet | C26: Nostro Sito | D26: Green System Srl | E26: Impresa edile / Artigiano | F26: 3468468539 | G26: utc@greensystemsrl.com | H26: Savona | I26: SV | J26: RIFIUTI | K26: Smaltimento rifiuti pericolosi e non pericolosi | L26: Rifiuti | M26: DA VERIFICARE | R26: 4 | S26: Registro chiamate 2026 – motivo 'RIFIUTI' – tipologia 'Imp. Edile' – esito da inserire | T26: Zone senza striscioni/cartelloni
A27: 46056 | B27: Italiaonline | D27: Feliziani Carlo | E27: Privato | F27: 3397275239 | G27: carlo.felizianitab@gmail.com | H27: Andora | I27: SV | J27: SPURGHI E RETI | K27: Rinnovamento non distruttivo tubazioni (relining) | L27: Relining | M27: DA VERIFICARE | R27: 33 | S27: Registro chiamate 2026 – motivo 'RELINING' – tipologia 'Privato' – esito da inserire | T27: Zone senza striscioni/cartelloni
A28: 46057 | B28: Internet | C28: Nostro Sito | D28: Uzunov Srl | E28: Impresa edile / Artigiano | F28: 3318035418 | G28: uzunovsrl@gmail.com | H28: Finale Ligure | I28: SV | J28: RIFIUTI | K28: Smaltimento rifiuti pericolosi e non pericolosi | L28: Rifiuti | M28: DA VERIFICARE | R28: 4 | S28: Registro chiamate 2026 – motivo 'RIFIUTI' – tipologia 'Imp. Edile' – esito da inserire | T28: Zone senza striscioni/cartelloni
A29: 46061 | B29: Italiaonline | D29: Colaprico Alessandro | E29: Privato | F29: 3290183973 | G29: alessandro.colaprico@gmail.com | H29: Savona | I29: SV | J29: IGIENE IMPIANTI | K29: Pulizia canne fumarie (spazzacamino) | L29: Ispezione TV canne fumarie | M29: DA VERIFICARE | R29: 4 | S29: Registro chiamate 2026 – motivo 'IT CANNE' – tipologia 'Privato' – esito da inserire | T29: Zone senza striscioni/cartelloni
A30: 46062 | B30: Italiaonline | D30: Giommi Francesco | E30: Attività / Turismo | F30: 3534401472 | G30: renzanueva@gmail.com | H30: Finale Ligure | I30: SV | J30: DA SPECIFICARE | L30: Pulizia (specificare: cisterne, facciate, cappe…) | M30: DA VERIFICARE | R30: 34 | S30: Registro chiamate 2026 – motivo 'PULIZIA' – tipologia 'Attività' – esito da inserire | T30: Zone senza striscioni/cartelloni
A31: 46064 | B31: Italiaonline | D31: Mazzola Roberto | E31: Attività / Turismo | F31: 3204731050 | G31: info@mazzolamobili.it | H31: Dolceacqua | I31: IM | J31: BONIFICHE | K31: Rimozione e smaltimento amianto – eternit | L31: Amianto | M31: DA VERIFICARE | R31: 11 | S31: Registro chiamate 2026 – motivo 'AMIANTO' – tipologia 'Attività' – esito da inserire | T31: Zone senza striscioni/cartelloni
A32: 46070 | B32: Italiaonline | C32: Nostro Sito | D32: Giusto Giulia | E32: Privato | F32: 3474351879 | G32: giustogiulia@gmail.com | H32: Quiliano | I32: SV | J32: IGIENE IMPIANTI | K32: Pulizia canne fumarie (spazzacamino) | L32: Ispezione TV canne fumarie | M32: DA VERIFICARE | R32: 1 | S32: Registro chiamate 2026 – motivo 'IT CANNE' – tipologia 'Privato' – esito da inserire | T32: Zone senza striscioni/cartelloni
A33: 46070 | B33: Bus | C33: Nostro Sito | D33: Uzunov Adrian | E33: Impresa edile / Artigiano | F33: 3318035418 | G33: uzunovsrl@gmail.com | H33: Finale Ligure | I33: SV | J33: RIFIUTI | K33: Smaltimento rifiuti pericolosi e non pericolosi | L33: Rifiuti | M33: DA VERIFICARE | R33: 4 | S33: Registro chiamate 2026 – motivo 'RIFIUTI' – tipologia 'Imp. Edile' – esito da inserire | T33: Zone senza striscioni/cartelloni
A34: 46079 | B34: Italiaonline | C34: Nostro Sito | D34: Mai Stefano | E34: Privato | F34: 3333041279 | G34: stefanomai@gmail.com | H34: Zuccarello | I34: SV | J34: DISINFESTAZIONE | K34: Derattizzazione, disinfestazione insetti, disinfezione, sanificazione | L34: Derattizzazione | M34: DA VERIFICARE | R34: 34 | S34: Registro chiamate 2026 – motivo 'DERATIZZAZ' – tipologia 'Privato' – esito da inserire | T34: Zone senza striscioni/cartelloni
A35: 46080 | B35: Italiaonline | D35: Volpe Andrea | E35: Privato | F35: 3336347160 | G35: andrea.volpe@phd.unipi.it | H35: Boissano | I35: SV | J35: SPURGHI E RETI | K35: Rinnovamento non distruttivo tubazioni (relining) | L35: Relining | M35: DA VERIFICARE | R35: 33 | S35: Registro chiamate 2026 – motivo 'RELINING' – tipologia 'Privato' – esito da inserire | T35: Zone senza striscioni/cartelloni
A36: 46085 | B36: Internet | C36: Nostro Sito | D36: Nial Nizzoli Srl | E36: Impresa edile / Artigiano | F36: 3358021311 | G36: alberto.covri@nialnizzoli.com | H36: Calice Ligure | I36: SV | J36: RIFIUTI | K36: Smaltimento rifiuti pericolosi e non pericolosi | L36: Rifiuti | M36: DA VERIFICARE | R36: 4 | S36: Registro chiamate 2026 – motivo 'RIFIUTI' – tipologia 'Imp. Edile' – esito da inserire | T36: Zone senza striscioni/cartelloni
A37: 46093 | B37: Internet | C37: Nostro Sito | D37: Hpc Italia S.R.L. | E37: Azienda / Società | F37: 3771849892 | G37: arianna.russo@hpc.ag | H37: Milano | I37: MI | J37: DA SPECIFICARE | L37: Pulizia (specificare: cisterne, facciate, cappe…) | M37: DA VERIFICARE | R37: 4 | S37: Registro chiamate 2026 – motivo 'PULIZ.' – tipologia 'Società di' – esito da inserire | T37: Zone senza striscioni/cartelloni
A38: 46097 | B38: Internet | C38: Nostro Sito | D38: Edilservizi Srl | E38: Impresa edile / Artigiano | F38: 3288356330 | G38: paola.sirello@edilservizisrl.it | H38: Albissola | I38: SV | J38: BONIFICHE | K38: Rimozione e smaltimento amianto – eternit | L38: Amianto | M38: DA VERIFICARE | R38: 4 | S38: Registro chiamate 2026 – motivo 'AMIANTO' – tipologia 'Imp. Edile' – esito da inserire | T38: Zone senza striscioni/cartelloni
A39: 46097 | B39: Passaparola | D39: Turri Alice | E39: Attività / Turismo | F39: 3497721380 | H39: Finale Ligure | I39: SV | J39: RIFIUTI | K39: Smaltimento rifiuti pericolosi e non pericolosi | L39: Rifiuti | M39: DA VERIFICARE | R39: 4 | S39: Registro chiamate 2026 – motivo 'RIFIUTI' – tipologia 'Attività' – esito da inserire | T39: Zone senza striscioni/cartelloni
A40: 46097 | B40: Passaparola | D40: Enzo | E40: Privato | F40: +1(916)293-6674 | H40: Albenga | I40: SV | J40: SPURGHI E RETI | K40: Canaljet – autospurgo fosse biologiche, fognature, pozzetti, degrassatori | L40: Fognatura / spurgo | M40: DA VERIFICARE | R40: 34 | S40: Registro chiamate 2026 – motivo 'FOGNA' – tipologia 'Privato' – esito da inserire | T40: Albenga
A41: 46097 | B41: Internet | C41: Google | D41: Basadonne Antonella | E41: Attività / Turismo | F41: 3407815448 | H41: Savona | I41: SV | J41: RIFIUTI | K41: Smaltimento rifiuti pericolosi e non pericolosi | L41: Rifiuti | M41: DA VERIFICARE | R41: 34 | S41: Registro chiamate 2026 – motivo 'RIFIUTI' – tipologia 'Attività' – esito da inserire | T41: Zone senza striscioni/cartelloni
A42: 46097 | B42: Internet | C42: Google | D42: Danila Morgavi | E42: Privato | F42: 3664285078 | H42: Alessandria | I42: AL | J42: BONIFICHE | K42: Rimozione e smaltimento amianto – eternit | L42: Amianto | M42: DA VERIFICARE | R42: 34 | S42: Registro chiamate 2026 – motivo 'AMIANTO' – tipologia 'Privato' – esito da inserire | T42: Zone senza striscioni/cartelloni
A43: 46097 | B43: Passaparola | D43: Amoroso Alessio | E43: Privato | F43: 3534492059 | G43: alessioamoroso@icloud.com | H43: Noli | I43: SV | J43: IGIENE IMPIANTI | K43: Pulizia canne fumarie (spazzacamino) | L43: Ispezione TV canne fumarie | M43: DA VERIFICARE | R43: 1 | S43: Registro chiamate 2026 – motivo 'IT CANNE' – tipologia 'Privato' – esito da inserire | T43: Zone senza striscioni/cartelloni
A44: 46097 | B44: Passaparola | D44: Husshin | E44: Attività / Turismo | F44: 3806545438 | H44: Imperia | I44: IM | J44: IGIENE IMPIANTI | K44: Pulizia canne fumarie (spazzacamino) | L44: Ispezione TV canne fumarie | M44: DA VERIFICARE | R44: 33 | S44: Registro chiamate 2026 – motivo 'IT CANNE' – tipologia 'Attività' – esito da inserire | T44: Imperia
A45: 46099 | B45: Passaparola | D45: Gatto Luca | E45: Privato | F45: 3886472046 | H45: Savona | I45: SV | J45: BONIFICHE | K45: Rimozione e smaltimento amianto – eternit | L45: Amianto | M45: DA VERIFICARE | R45: 4 | S45: Registro chiamate 2026 – motivo 'AMIANTO' – tipologia 'Privato' – esito da inserire | T45: Zone senza striscioni/cartelloni
A46: 46099 | B46: Altro | D46: Rodighiero Giacomo | E46: Attività / Turismo | F46: 3280844446 | J46: DA SPECIFICARE | L46: Motivo non indicato | M46: DA VERIFICARE | S46: Registro chiamate 2026 – motivo 'n.d.' – tipologia 'Attività' – esito da inserire | T46: Zone senza striscioni/cartelloni
A47: 46107 | B47: Internet | C47: Nostro Sito | D47: Pagliaffo Laura | E47: Privato | F47: 3493415040 | H47: Tovo S.G. | I47: SV | J47: DA SPECIFICARE | L47: Motivo non indicato | M47: DA VERIFICARE | S47: Registro chiamate 2026 – motivo 'n.d.' – tipologia 'Privato' – esito da inserire | T47: Zone senza striscioni/cartelloni
A48: 46107 | B48: Passaparola | D48: Vigo Ilma | E48: Privato | F48: 3487762409 | J48: BONIFICHE | K48: Rimozione e smaltimento amianto – eternit | L48: Amianto | M48: DA VERIFICARE | S48: Registro chiamate 2026 – motivo 'AMIANTO' – tipologia 'Privato' – esito da inserire | T48: Zone senza striscioni/cartelloni
A49: 46107 | B49: Passaparola | D49: Lucia Richeri | E49: Privato | F49: 3476499112 | H49: Calice Ligure | I49: SV | J49: BONIFICHE | K49: Rimozione e smaltimento amianto – eternit | L49: Amianto | M49: DA VERIFICARE | S49: Registro chiamate 2026 – motivo 'AMIANTO' – tipologia 'Privato' – esito da inserire | T49: Zone senza striscioni/cartelloni
A50: 46110 | B50: PgCasa (Italiaonline) | C50: Richiesta preventivo PgCasa | D50: Maram K. | E50: Privato | F50: 3926199199 | G50: maramkeshk5@gmail.com | H50: Sanremo | I50: IM | J50: DISINFESTAZIONE | K50: Derattizzazione, disinfestazione insetti, disinfezione, sanificazione | L50: Disinfestazione insetti | M50: DA RICONTATTARE | Q50: 8 | S50: esito da verificare | T50: Sanremo / Taggia / S.Lorenzo
A51: 46111 | B51: Italiaonline | C51: Nostro Sito | D51: Marcello Federico | E51: Condominio / Amministratore | F51: 3468030580 | G51: marcello.federico@tim.it | H51: Savona | I51: SV | J51: SPURGHI E RETI | K51: Ispezioni televisive e mappature reti | L51: Ispezione | M51: DA VERIFICARE | S51: Registro chiamate 2026 – motivo 'ISPEZIONI' – tipologia 'Amm.ni' – esito da inserire | T51: Zone senza striscioni/cartelloni
A52: 46111 | B52: Italiaonline | C52: Nostro Sito | D52: Francesco Andreotti | E52: Privato | F52: 3408745237 | G52: andreotti.franc@gmail.com | H52: Laigueglia | I52: SV | J52: SPURGHI E RETI | K52: Canaljet – autospurgo fosse biologiche, fognature, pozzetti, degrassatori | L52: Fognatura / spurgo | M52: DA VERIFICARE | R52: 11 | S52: Registro chiamate 2026 – motivo 'FOGNA' – tipologia 'Privato' – esito da inserire | T52: Zone senza striscioni/cartelloni
A53: 46111 | B53: Passaparola | D53: Lucio Ruscoschi | E53: Impresa edile / Artigiano | F53: 3493852666 | H53: Savona | I53: SV | J53: RIFIUTI | K53: Smaltimento rifiuti pericolosi e non pericolosi | L53: Rifiuti | M53: DA VERIFICARE | R53: 4 | S53: Registro chiamate 2026 – motivo 'RIFIUTI' – tipologia 'Imp. Edile' – esito da inserire | T53: Zone senza striscioni/cartelloni
A54: 46111 | B54: Passaparola | D54: Paolo Quattrocolo | E54: Privato | F54: 3420605107 | H54: Loano | I54: SV | J54: RIFIUTI | K54: Smaltimento rifiuti pericolosi e non pericolosi | L54: Rifiuti | M54: DA VERIFICARE | R54: 4 | S54: Registro chiamate 2026 – motivo 'RIFIUTI' – tipologia 'Privato' – esito da inserire | T54: Loano / Borghetto / Pietra
A55: 46111 | B55: PgCasa (Italiaonline) | C55: Richiesta preventivo PgCasa | D55: Giovanni P. | E55: Privato | F55: 3395955939 | G55: giannipoggio@gmail.com | H55: Borghetto Santo Spirito | I55: SV | J55: DISINFESTAZIONE | K55: Derattizzazione, disinfestazione insetti, disinfezione, sanificazione | L55: Disinfestazione insetti | M55: DA RICONTATTARE | Q55: 8 | S55: Sentito per telefono 01/04 (Contini) – esito da verificare | T55: Loano / Borghetto / Pietra
A56: 46112 | B56: Passaparola | D56: Giovanna Carlutto | E56: Privato | F56: 3447968824 | H56: Coldirodi | I56: IM | J56: BONIFICHE | K56: Rimozione e smaltimento amianto – eternit | L56: Amianto | M56: DA VERIFICARE | R56: 11 | S56: Registro chiamate 2026 – motivo 'AMIANTO' – tipologia 'Privato' – esito da inserire | T56: Sanremo / Taggia / S.Lorenzo
A57: 46112 | B57: Internet | C57: Google | D57: Vincenzo Fassone | E57: Privato | F57: 3336646033 | H57: Giusvalla | I57: SV | J57: RIFIUTI | K57: Smaltimento rifiuti pericolosi e non pericolosi | L57: Rifiuti | M57: DA VERIFICARE | R57: 4 | S57: Registro chiamate 2026 – motivo 'RIFIUTI' – tipologia 'Privato' – esito da inserire | T57: Zone senza striscioni/cartelloni
A58: 46115 | B58: Internet | C58: Nostro Sito | D58: Stefania Stasi | E58: Privato | F58: 3400732664 | G58: stefanis.505@gmail.com | H58: Ceriale | I58: SV | J58: RIFIUTI | K58: Smaltimento rifiuti pericolosi e non pericolosi | L58: Rifiuti | M58: DA VERIFICARE | R58: 4 | S58: Registro chiamate 2026 – motivo 'RIFIUTI' – tipologia 'Privato' – esito da inserire | T58: Zone senza striscioni/cartelloni
A59: 46119 | B59: Italiaonline | D59: Luca Murialdo | E59: Privato | F59: 3497195892 | G59: luca.murialdo@tiscali.it | H59: Savona | I59: SV | J59: BONIFICHE | K59: Rimozione e smaltimento amianto – eternit | L59: Amianto | M59: DA VERIFICARE | R59: 4 | S59: Registro chiamate 2026 – motivo 'AMIANTO' – tipologia 'Privato' – esito da inserire | T59: Zone senza striscioni/cartelloni
A60: 46120 | B60: Internet | D60: Geri Maura | E60: Privato | F60: 3293903231 | H60: Carbuta | I60: SV | J60: RIFIUTI | K60: Smaltimento rifiuti pericolosi e non pericolosi | L60: Rifiuti | M60: DA VERIFICARE | R60: 4 | S60: Registro chiamate 2026 – motivo 'RIFIUTI' – tipologia 'Privato' – esito da inserire | T60: Zone senza striscioni/cartelloni
A61: 46120 | B61: Italiaonline | D61: Gian Piero Aicardi | E61: Privato | F61: 3356069535 | H61: Magliolo | I61: SV | J61: RIFIUTI | K61: Smaltimento rifiuti pericolosi e non pericolosi | L61: Rifiuti | M61: DA VERIFICARE | R61: 34 | S61: Registro chiamate 2026 – motivo 'RIFIUTI' – tipologia 'Privato' – esito da inserire | T61: Zone senza striscioni/cartelloni
A62: 46120 | B62: Passaparola | D62: Bonardo Daniele | E62: Privato | F62: 3405501217 | H62: Borgio Verezzi | I62: SV | J62: DISINFESTAZIONE | K62: Derattizzazione, disinfestazione insetti, disinfezione, sanificazione | L62: Vespe | M62: DA VERIFICARE | S62: Registro chiamate 2026 – motivo 'VESPE' – tipologia 'Privato' – esito da inserire | T62: Zone senza striscioni/cartelloni
A63: 46122 | B63: Passaparola | D63: Raimondo Ratico' | E63: Impresa edile / Artigiano | F63: 3206255070 | J63: BONIFICHE | K63: Rimozione e smaltimento amianto – eternit | L63: Amianto | M63: DA VERIFICARE | R63: 11 | S63: Registro chiamate 2026 – motivo 'AMIANTO' – tipologia 'Imp. Edile' – esito da inserire | T63: Zone senza striscioni/cartelloni
A64: 46122 | B64: Internet | C64: Nostro Sito | D64: Avci Sabri | E64: Impresa edile / Artigiano | F64: 3291577998 | H64: Imperia | I64: IM | J64: RIFIUTI | K64: Smaltimento rifiuti pericolosi e non pericolosi | L64: Rifiuti | M64: DA VERIFICARE | R64: 33 | S64: Registro chiamate 2026 – motivo 'RIFIUTI' – tipologia 'Imp. Edile' – esito da inserire | T64: Imperia
A65: 46125 | B65: Internet | C65: Nostro Sito | D65: Fedon Mirko | E65: Privato | F65: 3356702190 | H65: Bardino Vecchio | I65: SV | J65: SPURGHI E RETI | K65: Canaljet – autospurgo fosse biologiche, fognature, pozzetti, degrassatori | L65: Fognatura / spurgo | M65: DA VERIFICARE | R65: 34 | S65: Registro chiamate 2026 – motivo 'FOGNA' – tipologia 'Privato' – esito da inserire | T65: Zone senza striscioni/cartelloni
A66: 46126 | B66: Italiaonline | C66: Nostro Sito | D66: Carla Bogliolo | E66: Privato | F66: 3297486517 | H66: Roccaverano | I66: AT | J66: BONIFICHE | K66: Rimozione e smaltimento amianto – eternit | L66: Amianto | M66: DA VERIFICARE | R66: 4 | S66: Registro chiamate 2026 – motivo 'AMIANTO' – tipologia 'Privato' – esito da inserire | T66: Zone senza striscioni/cartelloni
A67: 46127 | B67: Italiaonline | C67: Nostro Sito | D67: Riccardo Campi | E67: Privato | F67: 3495238497 | G67: rikic1979@gmai.com | H67: Plodio | I67: SV | J67: BONIFICHE | K67: Rimozione e smaltimento amianto – eternit | L67: Amianto | M67: DA VERIFICARE | R67: 4 | S67: Registro chiamate 2026 – motivo 'AMIANTO' – tipologia 'Privato' – esito da inserire | T67: Zone senza striscioni/cartelloni
A68: 46129 | B68: Pubblicità Automezzi | C68: Nostro Sito | D68: Gaggero Sergio | E68: Privato | F68: 3384308189 | H68: Rialto | I68: SV | J68: BONIFICHE | K68: Rimozione e smaltimento amianto – eternit | L68: Amianto | M68: DA VERIFICARE | R68: 34 | S68: Registro chiamate 2026 – motivo 'AMIANTO' – tipologia 'Privato' – esito da inserire | T68: Zone senza striscioni/cartelloni
A69: 46129 | B69: Italiaonline | D69: Antonella Pesce | E69: Privato | F69: 3284777458 | H69: Albenga | I69: SV | J69: BONIFICHE | K69: Rimozione e smaltimento amianto – eternit | L69: Amianto | M69: DA VERIFICARE | R69: 33 | S69: Registro chiamate 2026 – motivo 'AMIANTO' – tipologia 'Privato' – esito da inserire | T69: Albenga
A70: 46129 | B70: Pagine Gialle | C70: Pagine Gialle | D70: Genitoni Claudio Isaia | E70: Privato | F70: 3478310397 | H70: Loano | I70: SV | J70: SPURGHI E RETI | K70: Canaljet – autospurgo fosse biologiche, fognature, pozzetti, degrassatori | L70: Fognatura / spurgo | M70: DA VERIFICARE | R70: 34 | S70: Registro chiamate 2026 – motivo 'FOGNA' – tipologia 'Privato' – esito da inserire | T70: Loano / Borghetto / Pietra
A71: 46132 | B71: Italiaonline | C71: Nostro Sito | D71: Marangon Anna | E71: Privato | F71: 3286777421 | G71: maria.m48@icloud.com | H71: Toirano | I71: SV | J71: DA SPECIFICARE | L71: Analisi (specificare: acque potabili o rifiuti) | M71: DA VERIFICARE | R71: 4 | S71: Registro chiamate 2026 – motivo 'ANALISI' – tipologia 'Privato' – esito da inserire | T71: Zone senza striscioni/cartelloni
A72: 46132 | B72: PgCasa (Italiaonline) | C72: Richiesta preventivo PgCasa | D72: Felisia D. | E72: Privato | F72: 3407188935 | G72: felisiadandrea@libero.it | H72: Riva Ligure | I72: IM | J72: DISINFESTAZIONE | K72: Derattizzazione, disinfestazione insetti, disinfezione, sanificazione | L72: Disinfestazione pulci/zecche: Zecche sul cane e in casa | M72: DA RICONTATTARE | Q72: 8 | S72: Risposto 20/04: sopralluogo gratuito – esito da verificare | T72: Sanremo / Taggia / S.Lorenzo
A73: 46133 | B73: Italiaonline | C73: Nostro Sito | D73: Lucrezia Fasolo | E73: Privato | F73: 3201575201 | G73: lucreziafasolo94@gmail.com | H73: Savona | I73: SV | J73: RIFIUTI | K73: Smaltimento rifiuti pericolosi e non pericolosi | L73: Rifiuti | M73: DA VERIFICARE | R73: 4 | S73: Registro chiamate 2026 – motivo 'RIFIUTI' – tipologia 'Privato' – esito da inserire | T73: Zone senza striscioni/cartelloni
A74: 46134 | B74: Italiaonline | C74: Nostro Sito | D74: Ettore Carpentieri | E74: Privato | F74: 3406145339 | G74: ettore.carpentieri@gmail.com | H74: Quiliano | I74: SV | J74: DA SPECIFICARE | L74: Analisi (specificare: acque potabili o rifiuti) | M74: DA VERIFICARE | R74: 4 | S74: Registro chiamate 2026 – motivo 'ANALISI' – tipologia 'Privato' – esito da inserire | T74: Zone senza striscioni/cartelloni
A75: 46134 | B75: Italiaonline | C75: Nostro Sito | D75: Emily Mirch | E75: Privato | F75: 347369777 | G75: mirchemily@gmail.com | H75: Urbe | I75: SV | J75: RIFIUTI | K75: Smaltimento rifiuti pericolosi e non pericolosi | L75: Rifiuti | M75: DA VERIFICARE | R75: 4 | S75: Registro chiamate 2026 – motivo 'RIFIUTI' – tipologia 'Privato' – esito da inserire | T75: Zone senza striscioni/cartelloni
A76: 46136 | B76: Italiaonline | C76: Nostro Sito | D76: Martin Nilsson | E76: Privato | F76: +46768653193 | G76: martin.nilsson7210@gmail.com | H76: Badalucco | I76: IM | J76: IGIENE IMPIANTI | K76: Pulizia canne fumarie (spazzacamino) | L76: Ispezione TV canne fumarie | M76: DA VERIFICARE | R76: 38 | S76: Registro chiamate 2026 – motivo 'IT CANNE' – tipologia 'Privato' – esito da inserire | T76: Sanremo / Taggia / S.Lorenzo
A77: 46136 | B77: PgCasa (Italiaonline) | C77: Richiesta preventivo PgCasa | D77: Laura T. | E77: Privato | F77: 3471406840 | G77: tibald.laura@gmail.com | H77: Sanremo | I77: IM | J77: SPURGHI E RETI | K77: Canaljet – autospurgo fosse biologiche, fognature, pozzetti, degrassatori | L77: Spurgo fognature | M77: DA RICONTATTARE | Q77: 10 | S77: esito da verificare | T77: Sanremo / Taggia / S.Lorenzo
A78: 46139 | B78: Passaparola | C78: Nostro Sito | D78: Lavagna Francesco | E78: Privato | F78: 3402481456 | H78: Borgio V. | I78: SV | J78: DA SPECIFICARE | L78: Pulizia (specificare: cisterne, facciate, cappe…) | M78: DA VERIFICARE | R78: 34 | S78: Registro chiamate 2026 – motivo 'PULIZ.' – tipologia 'Privato' – esito da inserire | T78: Zone senza striscioni/cartelloni
A79: 46140 | B79: Internet | C79: Nostro Sito | D79: Alessandro | E79: Attività / Turismo | F79: 3285482540 | H79: Ceriale | I79: SV | J79: RIFIUTI | K79: Smaltimento rifiuti pericolosi e non pericolosi | L79: Rifiuti | M79: DA VERIFICARE | R79: 4 | S79: Registro chiamate 2026 – motivo 'RIFIUTI' – tipologia 'Campeggio' – esito da inserire | T79: Zone senza striscioni/cartelloni
A80: 46140 | B80: Internet | C80: Nostro Sito | D80: Ifex Group S.R.L. | E80: Impresa edile / Artigiano | F80: 019264113 | H80: Savona | I80: SV | J80: RIFIUTI | K80: Smaltimento rifiuti pericolosi e non pericolosi | L80: Rifiuti | M80: DA VERIFICARE | R80: 4 | S80: Registro chiamate 2026 – motivo 'RIFIUTI' – tipologia 'Imp. Edile' – esito da inserire | T80: Zone senza striscioni/cartelloni
A81: 46141 | B81: Italiaonline | C81: Nostro Sito | D81: Gadina Rossana | E81: Privato | F81: 0196898047 | J81: IGIENE IMPIANTI | K81: Pulizia canne fumarie (spazzacamino) | L81: Ispezione TV canne fumarie | M81: DA VERIFICARE | R81: 34 | S81: Registro chiamate 2026 – motivo 'IT CANNE' – tipologia 'Privato' – esito da inserire | T81: Zone senza striscioni/cartelloni
A82: 46142 | B82: Passaparola | C82: Finale Ligure | D82: Briozzo Mauro | E82: Privato | F82: 3335846991 | H82: Calizzano | I82: SV | J82: BONIFICHE | K82: Rimozione e smaltimento amianto – eternit | L82: Amianto | M82: DA VERIFICARE | R82: 4 | S82: Registro chiamate 2026 – motivo 'AMIANTO' – tipologia 'Privato' – esito da inserire | T82: Zone senza striscioni/cartelloni
A83: 46146 | B83: Passaparola | C83: Finale Ligure | D83: Luca Negro | E83: Privato | F83: 3393394253 | H83: Albisola | I83: SV | J83: DA SPECIFICARE | L83: Pulizia (specificare: cisterne, facciate, cappe…) | M83: DA VERIFICARE | R83: 34 | S83: Registro chiamate 2026 – motivo 'PULIZ.' – tipologia 'Privato' – esito da inserire | T83: Zone senza striscioni/cartelloni
A84: 46146 | B84: Quotidiani Online | C84: Nostro Sito | D84: La Monaca Carmelo | E84: Privato | F84: 3444879016 | H84: Calizzano | I84: SV | J84: SPURGHI E RETI | K84: Canaljet – autospurgo fosse biologiche, fognature, pozzetti, degrassatori | L84: Fognatura / spurgo | M84: DA VERIFICARE | R84: 4 | S84: Registro chiamate 2026 – motivo 'FOGNA' – tipologia 'Privato' – esito da inserire | T84: Zone senza striscioni/cartelloni
A85: 46147 | B85: Quotidiani Online | C85: Nostro Sito | D85: Mario Cimnotta | E85: Privato | F85: 3387877320 | H85: Loano | I85: SV | J85: RIFIUTI | K85: Smaltimento rifiuti pericolosi e non pericolosi | L85: Rifiuti | M85: DA VERIFICARE | R85: 4 | S85: Registro chiamate 2026 – motivo 'RIFIUTI' – tipologia 'Privato' – esito da inserire | T85: Loano / Borghetto / Pietra
A86: 46147 | B86: Passaparola | C86: Pagine Gialle | D86: Girardi Rosa | E86: Privato | F86: 3483631657 | H86: Loano | I86: SV | J86: SPURGHI E RETI | K86: Canaljet – autospurgo fosse biologiche, fognature, pozzetti, degrassatori | L86: Fognatura / spurgo | M86: DA VERIFICARE | R86: 34 | S86: Registro chiamate 2026 – motivo 'FOGNA' – tipologia 'Privato' – esito da inserire | T86: Loano / Borghetto / Pietra
A87: 46147 | B87: Passaparola | C87: Nostro Sito | D87: Paolo Berio | E87: Privato | F87: 3333362175 | H87: Andora | I87: SV | J87: DA SPECIFICARE | L87: Pulizia (specificare: cisterne, facciate, cappe…) | M87: DA VERIFICARE | R87: 33 | S87: Registro chiamate 2026 – motivo 'PULIZ.' – tipologia 'Privato' – esito da inserire | T87: Zone senza striscioni/cartelloni
A88: 46148 | B88: Passaparola | C88: Andora | D88: Maricchia Moreno | E88: Privato | F88: 0033609268459 | H88: Alassio | I88: SV | J88: IGIENE IMPIANTI | K88: Pulizia canne fumarie (spazzacamino) | L88: Ispezione TV canne fumarie | M88: DA VERIFICARE | R88: 34 | S88: Registro chiamate 2026 – motivo 'IT CANNE' – tipologia 'Privato' – esito da inserire | T88: Zone senza striscioni/cartelloni
A89: 46148 | B89: Internet | C89: Nostro Sito | D89: Marenco Daniele | E89: Privato | F89: 3467031155 | G89: marencodaniele@gmail.com | H89: Giustenice | I89: SV | J89: RIFIUTI | K89: Smaltimento rifiuti pericolosi e non pericolosi | L89: Rifiuti | M89: DA VERIFICARE | S89: Registro chiamate 2026 – motivo 'RIFIUTI' – tipologia 'Privato' – esito da inserire | T89: Zone senza striscioni/cartelloni
A90: 46148 | B90: Passaparola | D90: Oscar Sicbaldi | E90: Privato | F90: 3339872835 | H90: Genova | I90: GE | J90: DA SPECIFICARE | L90: Pulizia (specificare: cisterne, facciate, cappe…) | M90: DA VERIFICARE | R90: 33 | S90: Registro chiamate 2026 – motivo 'PULIZIA' – tipologia 'Privato' – esito da inserire | T90: Genova
A91: 46148 | B91: Internet | C91: Nostro Sito | D91: Pinotti Tiziano | E91: Privato | F91: 3201647496 | H91: Milano | I91: MI | J91: IGIENE IMPIANTI | K91: Pulizia canne fumarie (spazzacamino) | L91: Ispezione TV canne fumarie | M91: DA VERIFICARE | R91: 4 | S91: Registro chiamate 2026 – motivo 'IT CANNE' – tipologia 'Privato' – esito da inserire | T91: Zone senza striscioni/cartelloni
A92: 46150 | B92: Italiaonline | C92: Nostro Sito | D92: Popolo Adriana | E92: Privato | F92: 3384732925 | G92: adrianapopolo02@gmail.com | H92: Varazze | I92: SV | J92: DA SPECIFICARE | L92: Analisi (specificare: acque potabili o rifiuti) | M92: DA VERIFICARE | R92: 34 | S92: Registro chiamate 2026 – motivo 'ANALISI' – tipologia 'Privato' – esito da inserire | T92: Zone senza striscioni/cartelloni
A93: 46150 | B93: Passaparola | C93: Comune Di | D93: Osama | E93: Privato | F93: 3319514891 | H93: Pietra Ligure | I93: SV | J93: IGIENE IMPIANTI | K93: Pulizia canne fumarie (spazzacamino) | L93: Ispezione TV canne fumarie | M93: DA VERIFICARE | R93: 34 | S93: Registro chiamate 2026 – motivo 'IT CANNE' – tipologia 'Privato' – esito da inserire | T93: Loano / Borghetto / Pietra
A94: 46153 | B94: Italiaonline | C94: Nostro Sito | D94: Para Alessandro | E94: Privato | F94: 3478180977 | G94: para.alessandro@libero.it | H94: Millesimo | I94: SV | J94: RIFIUTI | K94: Smaltimento rifiuti pericolosi e non pericolosi | L94: Rifiuti | M94: DA VERIFICARE | R94: 4 | S94: Registro chiamate 2026 – motivo 'RIFIUTI' – tipologia 'Privato' – esito da inserire | T94: Zone senza striscioni/cartelloni
A95: 46155 | B95: Passaparola | C95: Comune Di | D95: Elisa Negro | E95: Privato | F95: 3339656775 | H95: Pietra Ligure | I95: SV | J95: SPURGHI E RETI | K95: Ricerca perdite | L95: Ricerca perdite | M95: DA VERIFICARE | R95: 34 | S95: Registro chiamate 2026 – motivo 'RICERCA' – tipologia 'Privato' – esito da inserire | T95: Loano / Borghetto / Pietra
A96: 46157 | B96: Passaparola | C96: Nostro Sito | D96: Cristina Pellizzola | E96: Privato | F96: 3473395230 | H96: Noli | I96: SV | J96: DISINFESTAZIONE | K96: Allontanamento volatili (piccioni, gabbiani) | L96: Volatili | M96: DA VERIFICARE | R96: 34 | S96: Registro chiamate 2026 – motivo 'VOLATILI' – tipologia 'Privato' – esito da inserire | T96: Zone senza striscioni/cartelloni
A97: 46157 | B97: Passaparola | D97: Silvia Risso | E97: Privato | F97: 3341659302 | H97: Sant'Ermete | I97: SV | J97: BONIFICHE | K97: Rimozione e smaltimento amianto – eternit | L97: Amianto | M97: DA VERIFICARE | R97: 34 | S97: Registro chiamate 2026 – motivo 'AMIANTO' – tipologia 'Privato' – esito da inserire | T97: Zone senza striscioni/cartelloni
A98: 46160 | B98: Passaparola | D98: Rolando Romeo | E98: Privato | F98: 3923048246 | H98: Cairo | I98: SV | J98: RIFIUTI | K98: Smaltimento rifiuti pericolosi e non pericolosi | L98: Rifiuti | M98: DA VERIFICARE | R98: 4 | S98: Registro chiamate 2026 – motivo 'RIFIUTI' – tipologia 'Privato' – esito da inserire | T98: Zone senza striscioni/cartelloni
A99: 46160 | B99: Passaparola | C99: Comune Di | D99: Rossi Corradi | E99: Privato | F99: 3335453074 | H99: Loano | I99: SV | J99: DA SPECIFICARE | L99: Pulizia (specificare: cisterne, facciate, cappe…) | M99: DA VERIFICARE | R99: 4 | S99: Registro chiamate 2026 – motivo 'PULIZ.' – tipologia 'Privato' – esito da inserire | T99: Loano / Borghetto / Pietra
A100: 46161 | B100: Passaparola | C100: Comune Di | D100: Edil Service | E100: Impresa edile / Artigiano | F100: 3899682857 | H100: Finale | I100: SV | J100: RIFIUTI | K100: Smaltimento rifiuti pericolosi e non pericolosi | L100: Rifiuti | M100: DA VERIFICARE | S100: Registro chiamate 2026 – motivo 'RIFIUTI' – tipologia 'Imp. Edile' – esito da inserire | T100: Zone senza striscioni/cartelloni
A101: 46162 | B101: Italiaonline | D101: Handanu Mirela | E101: Privato | F101: 3270681565 | H101: Sanremo | I101: IM | J101: BONIFICHE | K101: Rimozione e smaltimento amianto – eternit | L101: Amianto | M101: DA VERIFICARE | R101: 11 | S101: Registro chiamate 2026 – motivo 'AMIANTO' – tipologia 'Privato' – esito da inserire | T101: Sanremo / Taggia / S.Lorenzo
...

Sheet Servizi e obblighi
A1: Servizi e obblighi di legge
A2: Sintesi operativa per servizio – verificare sempre il testo vigente e l'iscrizione Albo aziendale
A4: N. | B4: Area | C4: Servizio | D4: Clienti tipici | E4: Codici EER tipici | F4: Autorizzazioni / qualifiche azienda | G4: Documenti per il lavoro e per il cliente | H4: Sicurezza lavoratori | I4: Mezzi e trasporto | J4: Note / punti critici | K4: Verifica interna (n. iscrizione, scadenza, chi)
A5: 1 | B5: SPURGHI E RETI | C5: Canaljet – autospurgo fosse biologiche, fognature, pozzetti, degrassatori | D5: Privati, condomini, ristoranti, aziende, Comuni | E5: 200304 fanghi fosse settiche; 200306 pulizia fognature; degrassatori: da classificare caso per caso | F5: Albo Gestori Ambientali cat. 4 (non pericolosi) e cat. 5 (pericolosi); iscrizione RENTRI | G5: Preventivo/ordine; FIR (digitale RENTRI dove dovuto); registro cronologico carico/scarico; 4ª copia/peso a destino; omologa impianto | H5: D.Lgs 81/08 (DVR, DPI, rischio biologico Titolo X); DPR 177/2011 se si entra in vasche, pozzi, fognature (impresa qualificata, 30% personale formato, preposto, addetto recupero) | I5: Mezzi iscritti all'Albo per i codici EER trasportati; ADR (autista con patentino ADR, consulente ADR, cisterna omologata) per rifiuti pericolosi | J5: Art. 230 c.5 D.Lgs 152/06: i rifiuti dalla pulizia manutentiva delle reti fognarie si considerano prodotti da chi fa la pulizia → FIR a nome nostro come produttore | K5: Albo MI03807: cat. 4D (non pericolosi) fino al 13/10/2031; cat. 5E (pericolosi) fino al 16/01/2030. Verificare targa + EER sul provvedimento.
A6: 2 | B6: SPURGHI E RETI | C6: Ispezioni televisive e mappature reti | D6: Condomini, amministratori, Comuni, imprese, assicurazioni | E6: Nessuno (se abbinata a spurgo vedi riga autospurgo) | F6: Nessuna autorizzazione ambientale specifica | G6: Rapporto di videoispezione con video/foto e planimetria; utile per pratiche assicurative e progetti | H6: D.Lgs 81/08; DPR 177/2011 se accesso a camerette; lavori su strada: segnaletica cantieri stradali (DI 22/01/2019) e formazione addetti | I6: Occupazione suolo/segnaletica se su strada pubblica (permesso Comune/Polizia locale) | J6: Servizio 'porta' per relining e spurghi: proporlo in pacchetto
A7: 3 | B7: SPURGHI E RETI | C7: Ricerca perdite | D7: Privati, condomini, aziende, assicurazioni | E7: Nessuno | F7: Nessuna specifica; se si interviene sugli impianti idraulici serve abilitazione DM 37/2008 | G7: Relazione tecnica con punti di perdita, foto/termografia | H7: D.Lgs 81/08 | I7: — | J7: Spesso richiesta dalle assicurazioni: relazione ben fatta = argomento di vendita
A8: 4 | B8: SPURGHI E RETI | C8: Rinnovamento non distruttivo tubazioni (relining) | D8: Condomini, privati, aziende, enti | E8: 170904 / 170203 se si producono scarti | F8: Abilitazione DM 37/2008 per impianti idrico-sanitari negli edifici | G8: Videoispezione prima/dopo; dichiarazione di conformità DM 37/08 dove dovuta; schede tecniche materiali (DM 174/2004 se acqua potabile); garanzia | H8: D.Lgs 81/08; uso resine: schede di sicurezza, ventilazione; DPR 177/2011 se in spazio confinato | I8: — | J8: Vendere sempre con videoispezione iniziale e finale
A9: 5 | B9: SPURGHI E RETI | C9: Noleggio bagni chimici | D9: Cantieri, eventi, Comuni | E9: 200304 reflui | F9: Albo cat. 4 per il trasporto reflui; RENTRI | G9: Contratto di noleggio; FIR per lo svuotamento; registro | H9: D.Lgs 81/08 (rischio biologico) | I9: Mezzo autospurgo iscritto all'Albo; permesso suolo pubblico per eventi | J9: Per i cantieri il bagno è obbligo del committente/impresa (D.Lgs 81/08, Allegato XIII) | K9: Albo MI03807: cat. 4D (non pericolosi) fino al 13/10/2031. Verificare targa + EER sul provvedimento.
A10: 6 | B10: RIFIUTI | C10: Smaltimento rifiuti pericolosi e non pericolosi | D10: Aziende, officine, cantieri, enti, porti | E10: Tutti i codici autorizzati sull'iscrizione Albo (vedi pagina Codici CER del sito) | F10: Albo cat. 4 / cat. 5; cat. 8 se si fa intermediazione senza detenzione; RENTRI (iscrizione e diritto annuale) | G10: Classificazione del rifiuto e analisi di caratterizzazione; omologa impianto; FIR digitale RENTRI (obbligatorio dal 13/02/2026 per gli iscritti); registro cronologico; MUD annuale | H10: D.Lgs 81/08 (rischio chimico Titolo IX, DPI) | I10: ADR per pericolosi: patentino autista, consulente ADR, etichettatura colli, documento di trasporto ADR | J10: Controllare che il codice EER sia sull'iscrizione Albo del mezzo PRIMA di accettare il lavoro | K10: Albo MI03807: cat. 4D (non pericolosi) fino al 13/10/2031; cat. 5E (pericolosi) fino al 16/01/2030; cat. 8C (intermediazione) fino al 13/10/2031. Verificare targa + EER sul provvedimento.
A11: 7 | B11: RIFIUTI | C11: Locazione cassoni scarrabili | D11: Cantieri, privati per sgomberi, aziende, condomini | E11: 170904, 170107, 200307 ingombranti, 150106, 170201… | F11: Albo cat. 4 (e cat. 5 se pericolosi); RENTRI | G11: Ordine con codice EER dichiarato dal cliente; FIR al ritiro; omologa impianto | H11: D.Lgs 81/08 (carico/scarico, movimentazione) | I11: Scarrabile iscritto; permesso occupazione suolo pubblico se cassone su strada (a cura cliente/Comune) e segnaletica | J11: Il rifiuto resta del cliente-produttore fino al ritiro: dichiarare subito il codice; vietato mescolare rifiuti diversi (art. 187 D.Lgs 152/06) | K11: Albo MI03807: cat. 4D (non pericolosi) fino al 13/10/2031; cat. 5E (pericolosi) fino al 16/01/2030. Verificare targa + EER sul provvedimento.
A12: 8 | B12: RIFIUTI | C12: Trasporto e smaltimento inerti / terre e rocce da scavo | D12: Imprese edili, privati con lavori, Comuni | E12: 170904 misti da costruzione e demolizione; 170107; 170504 terre e rocce | F12: Albo cat. 4; RENTRI; per impianto V.A.L.: autorizzazione impianto e End of Waste DM 152/2022 | G12: Terre e rocce: DPR 120/2017 (sottoprodotto con dichiarazione di utilizzo, oppure rifiuto con FIR); FIR; omologa impianto | H12: D.Lgs 81/08 Titolo IV cantieri (POS se lavoriamo in cantiere) | I12: Scarrabile/cassonato iscritto all'Albo | J12: Procedura interna: oltre 50 t di 170904 sullo stesso cantiere serve analisi valida + omologa (skill verifica-soglia-analisi) | K12: Albo MI03807: cat. 4D (non pericolosi) fino al 13/10/2031. Verificare targa + EER sul provvedimento.
A13: 9 | B13: RIFIUTI | C13: Microraccolta rifiuti | D13: Piccole aziende, artigiani, studi, officine | E13: Vari (oli, filtri, imballaggi, toner, ecc.) | F13: Albo cat. 4 / cat. 5; RENTRI | G13: Art. 193 D.Lgs 152/06: microraccolta con un unico FIR per il percorso con più produttori; il cliente rispetta il deposito temporaneo (art. 185-bis) | H13: D.Lgs 81/08 | I13: ADR per pericolosi (spesso in esenzione parziale 1.1.3.6: verificare con consulente ADR) | J13: Ottimo per contratti annui con ritiri programmati | K13: Albo MI03807: cat. 1F (urbani) fino al 14/04/2027; cat. 4D (non pericolosi) fino al 13/10/2031; cat. 5E (pericolosi) fino al 16/01/2030. Verificare targa + EER sul provvedimento.
A14: 10 | B14: RIFIUTI | C14: Lavorazione rifiuti da costruzione e demolizione (V.A.L. – Cisano sul Neva) | D14: Imprese edili, trasportatori | E14: 170904, 170107, 170302… | F14: Autorizzazione impianto (art. 208 o procedura semplificata artt. 214-216 D.Lgs 152/06); End of Waste DM 152/2022 | G14: Omologa in ingresso, registro, dichiarazione di conformità per l'aggregato recuperato | H14: D.Lgs 81/08 | I14: — | J14: Sito separato valcenesi.it: collegare i due servizi nei pacchetti cantiere
A15: 11 | B15: BONIFICHE | C15: Bonifiche ambientali e discariche abusive | D15: Comuni, enti, aziende, privati (terreni) | E15: Vari, spesso misti e pericolosi | F15: Albo cat. 9 (bonifica siti) + cat. 4/5 trasporto | G15: D.Lgs 152/06 Parte IV Titolo V (art. 242 e segg.): caratterizzazione, progetto di bonifica approvato, certificazione finale Provincia/Città metropolitana; per discariche abusive: ordinanza sindacale (art. 192) | H15: D.Lgs 81/08 Titolo IV (PSC/POS), rischio chimico e biologico | I15: ADR per pericolosi | J15: Lavori pubblici: requisiti di gara (SOA, DURC, ecc.) | K15: Albo MI03807: cat. 9E (bonifica siti) fino al 14/04/2027; cat. 4D (non pericolosi) fino al 13/10/2031; cat. 5E (pericolosi) fino al 16/01/2030. Verificare targa + EER sul provvedimento.
A16: 12 | B16: BONIFICHE | C16: Rimozione e smaltimento amianto – eternit | D16: Privati, condomini, aziende, agricoltori, enti | E16: 170605* materiali da costruzione contenenti amianto; 170601* | F16: Albo cat. 10A (compatto: eternit) / 10B (friabile) + cat. 5 trasporto | G16: Piano di lavoro all'ASL (art. 256 D.Lgs 81/08) almeno 30 giorni prima dell'inizio (salvo urgenza); notifica art. 250; FIR; per friabile: certificato di restituibilità (DM 6/9/1994) | H16: D.Lgs 81/08 Titolo IX Capo III: formazione DPR 8/8/1994 (operatore e coordinatore), sorveglianza sanitaria, registro esposti, DPI FFP3/tute | I16: ADR (UN 2590 amianto crisotilo / UN 2212 anfiboli); mezzo cat. 5 | J16: Tempi del piano di lavoro: dirlo al cliente in fase di preventivo | K16: Albo MI03807: cat. 10B classe C (amianto) fino al 16/01/2030; cat. 5E (pericolosi) fino al 16/01/2030. Verificare targa + EER sul provvedimento.
A17: 13 | B17: BONIFICHE | C17: Pulizia cisterne e serbatoi, inertizzazione e vetrificazione | D17: Condomini (ex gasolio), aziende, distributori, privati | E17: 130701* gasolio; 160708* rifiuti contenenti olio; 130502* | F17: Albo cat. 4 / 5; RENTRI | G17: Certificato di bonifica/gas-free a fine lavori; documentazione per dismissione serbatoio (Comune/VVF secondo i casi); FIR | H17: DPR 177/2011 OBBLIGATORIO (spazio confinato): impresa qualificata, procedura, rilevatore gas, preposto, addetto recupero; ATEX se atmosfera esplosiva | I17: ADR (cisterna/colli per pericolosi) | J17: Servizio ad alto margine per condomini che passano dal gasolio al metano/pompa di calore | K17: Albo MI03807: cat. 4D (non pericolosi) fino al 13/10/2031; cat. 5E (pericolosi) fino al 16/01/2030. Verificare targa + EER sul provvedimento.
A18: 14 | B18: DISINFESTAZIONE | C18: Derattizzazione, disinfestazione insetti, disinfezione, sanificazione | D18: Privati, condomini, ristoranti/HACCP, aziende alimentari, enti, barche | E18: 150110* imballaggi contaminati; esche esauste | F18: L. 82/1994 e DM 274/1997: requisiti tecnico-professionali e responsabile tecnico per disinfezione, disinfestazione, derattizzazione e sanificazione (iscrizione Registro imprese per le attività) | G18: Solo prodotti autorizzati (biocidi Reg. UE 528/2012 o PMC DPR 392/1998, con n. di registrazione in scheda); scheda di intervento con prodotto, dose, aree; per clienti alimentari (Reg. CE 852/2004 HACCP): piano di monitoraggio, planimetria postazioni, report periodici | H18: D.Lgs 81/08 rischio chimico, schede di sicurezza, DPI | I18: Trasporto prodotti in quantità limitate (verificare esenzioni ADR) | J18: Rodenticidi anticoagulanti: solo operatori professionali e in erogatori chiusi secondo l'autorizzazione del prodotto
A19: 15 | B19: DISINFESTAZIONE | C19: Allontanamento volatili (piccioni, gabbiani) | D19: Condomini, enti, aziende, capannoni | E19: Guano: rifiuto da smaltire (codice da classificare) | F19: L. 157/1992 tutela fauna: vietato uccidere o catturare; ammessi solo sistemi incruenti (reti, aghi, dissuasori) | G19: Relazione con sistema installato; rispetto ordinanze comunali sui colombi | H19: D.Lgs 81/08 rischio biologico (guano) e lavori in quota (Titolo IV): PLE con patentino, DPI anticaduta, ponteggi con PiMUS | I19: — | J19: Abbinare pulizia/sanificazione del guano
A20: 16 | B20: IGIENE IMPIANTI | C20: Pulizia e igienizzazione cappe cucine (civili e industriali) | D20: Ristoranti, mense, hotel, industrie alimentari | E20: Grassi/filtri: da classificare | F20: Nessuna autorizzazione specifica; iscrizione attività pulizia L. 82/1994 | G20: Rapporto di intervento con foto prima/dopo (serve al cliente per HACCP Reg. CE 852/2004 e per prevenzione incendi DM 3/9/2021 – controlli e manutenzione) | H20: D.Lgs 81/08 (lavori in quota, prodotti chimici) | I20: — | J20: Periodicità consigliata semestrale/trimestrale in base all'uso: base per contratto annuo
A21: 17 | B21: IGIENE IMPIANTI | C21: Pulizia canalizzazioni aerauliche e condizionatori (anche imbarcazioni) | D21: Uffici, hotel, strutture sanitarie, barche | E21: Da classificare | F21: Nessuna specifica | G21: Accordo Stato-Regioni 7/2/2013 (igiene impianti trattamento aria): ispezione, pulizia, verbale; Linee guida Legionella 2015 | H21: D.Lgs 81/08 rischio biologico | I21: — | J21: Strutture ricettive/sanitarie hanno obbligo di valutazione rischio Legionella: forte leva commerciale
A22: 18 | B22: IGIENE IMPIANTI | C22: Pulizia canne fumarie (spazzacamino) | D22: Privati, condomini, ristoranti/pizzerie | E22: Fuliggine: da classificare | F22: Nessuna autorizzazione ambientale; se si interviene sull'impianto: abilitazione DM 37/2008 | G22: Rapporto di controllo secondo UNI 10847; annotazione sul libretto di impianto (DPR 74/2013) | H22: D.Lgs 81/08 lavori in quota su tetti (linee vita, DPI anticaduta) | I22: — | J22: Forni a legna/pizzerie: pulizia periodica richiesta anche dalle assicurazioni
A23: 19 | B23: IGIENE IMPIANTI | C23: Controllo acque potabili | D23: Condomini, hotel, ristoranti, aziende alimentari, piscine | E23: — | F23: Analisi da laboratorio accreditato ACCREDIA | G23: D.Lgs 18/2023 (acque destinate al consumo umano); per HACCP: autocontrollo; Linee guida Legionella 2015 per strutture a rischio | H23: D.Lgs 81/08 | I23: — | J23: Proporlo insieme a cappe e pest control ai clienti alimentari
A24: 20 | B24: IGIENE IMPIANTI | C24: Pulizia facciate e rimozione graffiti | D24: Condomini, Comuni, negozi | E24: Acque di lavaggio e residui: rifiuto | F24: Nessuna specifica; su edifici vincolati: autorizzazione Soprintendenza (D.Lgs 42/2004) | G24: Acque di lavaggio non scaricabili in fognatura bianca: raccolta e smaltimento con FIR; permesso suolo pubblico | H24: D.Lgs 81/08 lavori in quota: PLE (patentino Accordo Stato-Regioni 2012), ponteggi con PiMUS | I24: —
A25: 21 | B25: NAUTICA | C25: Pulizia serbatoi barche e yacht (acque nere, grigie, sentine) e analisi/pulizia tubazioni | D25: Cantieri navali, marina, armatori, porti turistici | E25: 130403* oli di sentina; 160708*; 200304 acque nere | F25: Albo cat. 4 / 5; autorizzazione ad operare in porto (Capitaneria/Autorità portuale/concessionario) | G25: D.Lgs 197/2021 (impianti portuali di raccolta rifiuti delle navi); FIR; ricevuta di conferimento per l'imbarcazione | H25: D.Lgs 81/08; DPR 177/2011 per interni serbatoi | I25: ADR per oli di sentina | J25: Pacchetto nautica: serbatoi + derattizzazione + canalizzazioni aria | K25: Albo MI03807: cat. 4D (non pericolosi) fino al 13/10/2031; cat. 5E (pericolosi) fino al 16/01/2030. Verificare targa + EER sul provvedimento.
A26: 22 | B26: CONSULENZA | C26: Consulenze ambientali | D26: Aziende, cantieri, enti | E26: — | F26: Nessuna autorizzazione obbligatoria; per consulenza ADR serve il certificato di consulente ADR | G26: Supporto a RENTRI, MUD, registro, classificazione rifiuti, pratiche terre e rocce, piani amianto | H26: — | I26: — | J26: Vendere come servizio aggiuntivo 'pratiche comprese' (già scritto sul sito)
A27: 23 | B27: CONSULENZA | C27: Rilevazioni termografiche e certificazione energetica (APE) | D27: Privati, condomini, agenzie immobiliari | E27: — | F27: APE: certificatore energetico abilitato (DPR 75/2013, D.Lgs 192/2005) e invio al catasto APE regionale Liguria; termografia: operatore certificato UNI EN ISO 9712 consigliato | G27: APE registrato; rapporto termografico | H27: D.Lgs 81/08 | I27: — | J27: Verificare chi in azienda ha l'abilitazione: se nessuno, togliere dal modulo del sito o appoggiarsi a un tecnico esterno

Sheet Iscrizione Albo
A1: Iscrizione Albo Nazionale Gestori Ambientali – n. MI03807
A2: Sezione regionale Lombardia (sede legale Via Fieno 3, Milano) – fonte: provvedimenti in Desktop\claude servizi ecologici\autorizzazioni\$AUTORIZZAZIONI
A4: Categoria | B4: Classe | C4: Cosa consente | D4: Inizio validità | E4: Fine validità | F4: Giorni alla scadenza | G4: Stato | H4: Responsabile tecnico | I4: Provvedimento / file | J4: Servizi collegati
A5: 1 | B5: F – popolazione servita < 5.000 ab. | C5: Raccolta e trasporto rifiuti urbani | D5: 44665 | E5: 46491 | F5: =E5-TODAY() -> 201 | G5: =IF(F5<0,"SCADUTA",IF(F5<=270,"RINNOVARE ORA",IF(D5>TODAY(),"IN VIGORE DAL "&TEXT(D5,"dd/mm/yyyy"),"VALIDA"))) -> RINNOVARE ORA | H5: Arecco Bruna | I5: Prot. 26489/2022 del 28/02/2022 – AUT MI03807 DEL 14042022 CAT 1F.pdf | J5: Microraccolta, ingombranti, rifiuti urbani
A6: 4 | B6: D – da 6.000 a < 15.000 t/anno | C6: Raccolta e trasporto rifiuti speciali NON pericolosi (cassoni e cisterne) | D6: 46308 | E6: 48134 | F6: =E6-TODAY() -> 1844 | G6: =IF(F6<0,"SCADUTA",IF(F6<=270,"RINNOVARE ORA",IF(D6>TODAY(),"IN VIGORE DAL "&TEXT(D6,"dd/mm/yyyy"),"VALIDA"))) -> IN VIGORE DAL 13/10/2026 | H6: Arecco Bruna | I6: Rinnovo prot. 169389/2026 del 24/06/2026 – MI03807_PR_2026_169389_rinnovo cat 4.pdf | J6: Autospurgo, cassoni, inerti, bagni chimici, rifiuti non pericolosi
A7: 5 | B7: E – da 3.000 a < 6.000 t/anno | C7: Raccolta e trasporto rifiuti speciali PERICOLOSI | D7: 45673 | E7: 47499 | F7: =E7-TODAY() -> 1209 | G7: =IF(F7<0,"SCADUTA",IF(F7<=270,"RINNOVARE ORA",IF(D7>TODAY(),"IN VIGORE DAL "&TEXT(D7,"dd/mm/yyyy"),"VALIDA"))) -> VALIDA | H7: Arecco Bruna | I7: Prot. 125876/2024 del 19/11/2024 – AUT MI03807 DEL 16012025 CAT 5E.pdf | J7: Rifiuti pericolosi, amianto, oli, cisterne, sentine
A8: 8 | B8: C | C8: Intermediazione e commercio di rifiuti senza detenzione | D8: 46308 | E8: 48134 | F8: =E8-TODAY() -> 1844 | G8: =IF(F8<0,"SCADUTA",IF(F8<=270,"RINNOVARE ORA",IF(D8>TODAY(),"IN VIGORE DAL "&TEXT(D8,"dd/mm/yyyy"),"VALIDA"))) -> IN VIGORE DAL 13/10/2026 | H8: Sciutto Chiara (affiancamento) | I8: Cartella 'AUTORIZZAZIONE CAT. 8 C DEL 13 10 2026 SCADE IL13 10 2031' (PDF scansione: date dal nome cartella) | J8: Smaltimenti affidati a terzi, consulenza
A9: 9 | B9: E | C9: Bonifica di siti | D9: 44665 | E9: 46491 | F9: =E9-TODAY() -> 201 | G9: =IF(F9<0,"SCADUTA",IF(F9<=270,"RINNOVARE ORA",IF(D9>TODAY(),"IN VIGORE DAL "&TEXT(D9,"dd/mm/yyyy"),"VALIDA"))) -> RINNOVARE ORA | H9: Arecco Bruna / Sciutto Chiara | I9: Prot. 26488/2022 del 28/02/2022 – AUT MI03807 DEL 14042022 CAT 9E.pdf | J9: Bonifiche ambientali, discariche abusive
A10: 10B | B10: C | C10: Bonifica di beni contenenti amianto (materiali friabili e altri) | D10: 45673 | E10: 47499 | F10: =E10-TODAY() -> 1209 | G10: =IF(F10<0,"SCADUTA",IF(F10<=270,"RINNOVARE ORA",IF(D10>TODAY(),"IN VIGORE DAL "&TEXT(D10,"dd/mm/yyyy"),"VALIDA"))) -> VALIDA | H10: Arecco Bruna | I10: Prot. 125877/2024 del 19/11/2024 – AUT MI03807 DEL 16012025 CAT10BC.pdf | J10: Rimozione amianto – eternit
A11: 2-bis | B11: — | C11: Trasporto in conto proprio dei propri rifiuti | D11: 44592 | E11: 48244 | F11: =E11-TODAY() -> 1954 | G11: =IF(F11<0,"SCADUTA",IF(F11<=270,"RINNOVARE ORA",IF(D11>TODAY(),"IN VIGORE DAL "&TEXT(D11,"dd/mm/yyyy"),"VALIDA"))) -> VALIDA | H11: — | I11: Prot. 109294/2021 del 15/09/2021 – AUT MI03807 DEL 31012022 CAT 2BIS CONTO PROPRIO.pdf | J11: Rifiuti prodotti dall'azienda (manutenzioni)
A13: • Legale rappresentante: Arecco Bruna (amministratore unico) – 12 addetti dichiarati all'Albo (istanza 10/06/2026).
A14: • Istanze 2026 già presentate: inserimento codici CER cat. 5 (10/06), geolocalizzazione HB186JC (15/06), cancellazione mezzo (17/06), rinnovo cat. 4 e 8 (accolto 18/06/2026).
A15: • ATTENZIONE: cat. 1F e 9E scadono il 14/04/2027 → preparare la domanda di rinnovo (in genere va presentata prima della scadenza, con fideiussione aggiornata).
A16: • Prima di accettare un lavoro controllare che il codice EER e la targa del mezzo siano sul provvedimento della categoria giusta (4 = non pericolosi, 5 = pericolosi).
A17: • Cat. 10 e 5: per l'amianto servono entrambe (bonifica 10B + trasporto 5).

Sheet Obblighi trasversali
A1: Obblighi che valgono per tutta l'azienda
A2: Scadenziario: compilare le colonne gialle
A4: Ambito | B4: Obbligo | C4: Riferimento | D4: Periodicità / termine | E4: Scadenza (compilare) | F4: Responsabile
A5: Albo Gestori | B5: Iscrizione cat. 4/5 (e 8, 9, 10A/10B se svolte) con elenco mezzi e codici EER aggiornati; responsabile tecnico | C5: D.Lgs 152/06 art. 212; DM 120/2014 | D5: Rinnovo ogni 5 anni; diritto annuale entro 30 aprile; variazioni mezzi/EER prima di usarli | E5: 46491 | F5: Arecco Bruna (RT) – prossima: cat. 1F e 9E
A6: RENTRI | B6: Iscrizione, registro cronologico digitale, FIR digitale (dal 13/02/2026 solo digitale per gli iscritti; da trasportatore saper gestire anche i FIR cartacei dei produttori non iscritti) | C6: DM 59/2023; art. 188-bis e 193 D.Lgs 152/06 | D6: Diritto annuale entro 30 aprile; annotazioni registro entro 10 giorni
A7: MUD | B7: Dichiarazione annuale rifiuti trasportati/prodotti | C7: L. 70/1994 | D7: Annuale (normalmente 30 aprile)
A8: ADR | B8: Consulente ADR nominato, relazione annuale, patentini ADR autisti, equipaggiamento mezzi | C8: ADR / D.Lgs 35/2010 | D8: Relazione annuale; patentino ogni 5 anni
A9: Sicurezza | B9: DVR aggiornato (rischio biologico, chimico, amianto, spazi confinati, quota), RSPP, RLS, medico competente, formazione Accordo Stato-Regioni | C9: D.Lgs 81/08 | D9: Formazione: aggiornamento ogni 5 anni; visite secondo protocollo sanitario
A10: Spazi confinati | B10: Qualificazione impresa, procedura, formazione specifica e addestramento, attrezzature (rilevatori, tripode) | C10: DPR 177/2011 | D10: Addestramento periodico
A11: Mezzi | B11: Revisioni, cronotachigrafo, CQC e patenti C/CE autisti, assicurazioni, iscrizione mezzi all'Albo | C11: Codice della strada; Reg. UE 165/2014 | D11: Revisione annuale mezzi pesanti; CQC ogni 5 anni
A12: Disinfestazione | B12: Requisiti tecnico-professionali e responsabile tecnico per disinfestazione/derattizzazione/sanificazione | C12: L. 82/1994; DM 274/1997 | D12: Mantenere i requisiti; comunicare variazioni al Registro imprese
A13: DURC / appalti | B13: Regolarità contributiva; per enti pubblici requisiti di gara | C13: D.Lgs 36/2023 (Codice appalti) | D13: DURC validità 120 giorni
A14: Privacy contatti | B14: I contatti PgCasa/telefonate/moduli sono dati personali: informativa, uso solo per il preventivo richiesto, consenso separato per offerte promozionali, conservazione limitata | C14: Reg. UE 679/2016 (GDPR) | D14: Revisione periodica del Registro (cancellare contatti non clienti dopo il periodo stabilito)
A15: Qualità | B15: Certificazione ISO 9001 (indicata sul sito) | C15: UNI EN ISO 9001 | D15: Audit annuale; rinnovo triennale

Sheet Pacchetti
A1: Pacchetti per tipo di cliente
A2: Proposta commerciale: il 'perché conviene' è l'obbligo di legge che il pacchetto risolve
A4: Pacchetto | B4: Tipo cliente | C4: Servizi inclusi | D4: Frequenza | E4: Documenti che riceve il cliente | F4: Obbligo / problema che risolve | G4: Prezzi di listino 2025-26 (vendita, IVA esclusa, zona SV) | H4: Note commerciali
A5: CASA SERENA | B5: Privato | C5: Spurgo fossa biologica/pozzetti + videoispezione di controllo + 1 disinfestazione insetti o derattizzazione | D5: Annuale | E5: FIR dello spurgo, rapporto videoispezione, scheda intervento con prodotti autorizzati | F5: Fossa biologica da svuotare periodicamente (regolamenti comunali/ASL); smaltimento tracciato dei fanghi | G5: Pulizia fossa biologica 220 € (max 1 h) + smaltimento fanghi 0,16 €/kg liquidi; videoispezione furgone 100 €/h (min 3 h) + relazione 50 €; disinfestazione parti comuni 155 € | H5: Dai contatti PgCasa: metà spurghi, metà insetti → pacchetto su misura per i privati di SV e IM
A6: CONDOMINIO PROGRAMMATO | B6: Condominio / Amministratore | C6: Spurgo colonne e pozzetti, derattizzazione trimestrale, videoispezione, allontanamento volatili, cassone per sgomberi cantine | D6: Contratto annuo | E6: Report unico annuale per l'assemblea, FIR, schede interventi, relazione videoispezione | F6: Igiene parti comuni, responsabilità dell'amministratore, documenti pronti per assicurazione | G6: Derattizzazione parti comuni 160 € (max 4 erogatori, 3 passaggi); disinf.+derattiz. 200 € (min 10 condomini, 3 passaggi); spurgo 220 €/intervento; pulizia rete 120 €/h | H6: Agganciare gli amministratori: un contratto = molti stabili
A7: HACCP COMPLETO | B7: Ristorazione / Alimentare | C7: Pest control HACCP (monitoraggio mensile), pulizia degrassatore, pulizia cappe (semestrale), controllo acque potabili | D7: Mensile / semestrale | E7: Piano di monitoraggio con planimetria esche, report periodici, rapporto cappe con foto, analisi acqua, FIR | F7: Reg. CE 852/2004 (HACCP), prevenzione incendi cappe (DM 3/9/2021), D.Lgs 18/2023 acque | G7: Analisi acqua potabile D.Lgs 18/2023 180 € (con Legionella 250 €); canne fumarie/cappe attività 450 € (max 3 h); spurgo degrassatore 220 €; derattizzazione a contratto da valutare | H7: Il cliente supera i controlli ASL con i nostri documenti
A8: AZIENDA IN REGOLA | B8: Azienda / Industria | C8: Ritiri rifiuti programmati (microraccolta), classificazione e analisi, supporto RENTRI/FIR digitale e MUD, pulizia cisterne | D8: Mensile / a chiamata | E8: FIR digitali, registro, analisi di caratterizzazione, promemoria MUD | F8: D.Lgs 152/06 e RENTRI (FIR digitale dal 13/02/2026), deposito temporaneo art. 185-bis | G8: Smaltimento a €/kg da listino Rifiuti (es. 150110* 1,36 €/kg m.f. 200 €; 160107* 1,36 €/kg); analisi caratterizzazione solido 530 € / liquido 450 € | H8: Leva: 'pensiamo noi alle pratiche' (già promesso sul sito)
A9: CANTIERE CHIAVI IN MANO | B9: Impresa edile / Cantiere | C9: Cassoni scarrabili, trasporto inerti a V.A.L., bagni chimici, rimozione amianto, gestione terre e rocce | D9: Per durata cantiere | E9: FIR, omologhe, piano di lavoro amianto, documentazione terre e rocce DPR 120/2017 | F9: Codici EER corretti, soglia 50 t con analisi, piano amianto ASL 30 gg, bagni obbligatori in cantiere | G9: Scarrabile piccolo 110–160 €/viaggio secondo zona; noleggio cassone 3 €/g o 60 €/mese; 170904 16 €/t m.f. 50 €; amianto lastre da 17 €/m2 (100 m2) a 11 €/m2 (1000 m2) + piano di lavoro 250 € | H9: Filiera interna fino all'impianto V.A.L.: prezzo competitivo
A10: ENTE PUBBLICO | B10: Ente pubblico | C10: Spurgo reti e caditoie, videoispezioni e mappature, bonifica discariche abusive, allontanamento volatili, derattizzazione | D10: Appalto annuo / a chiamata | E10: Relazioni tecniche, mappature, FIR, certificazioni | F10: Manutenzione reti, igiene pubblica, rimozione rifiuti abbandonati (art. 192 D.Lgs 152/06) | G10: Ispezione TV con canal jet 150 €/h (min 3 h); pulizia rete 120 €/h; relazione 50 €; su appalto: prezzi di gara | H10: Partecipare a gare e MePA
A11: NAUTICA | B11: Nautica / Porto | C11: Svuotamento serbatoi acque nere/grigie e sentine, pulizia tubazioni, derattizzazione imbarcazioni, pulizia canalizzazioni aria | D11: Stagionale / a chiamata | E11: FIR / ricevuta conferimento, rapporto intervento | F11: D.Lgs 197/2021 rifiuti delle navi, igiene impianti aria | G11: Cassa gasolio e sentina 1.900 €; casse acque grigie/nere 1.500 €; gas-free 130 €/cassa; min. 4 ore | H11: Accordi con marina e cantieri navali
A12: PRONTO INTERVENTO 24H | B12: Tutti | C12: Spurgo urgente, disostruzione, allagamenti, infestazioni urgenti | D12: A chiamata | E12: FIR, rapporto intervento | F12: Emergenze igienico-sanitarie | G12: Festivo/notturno +50%, sabato +30% sulle tariffe spurghi | H12: Tariffa con diritto di chiamata notturno/festivo

Sheet Motivi
A1: Motivi lavoro non preso
A2: Usati dal menù a tendina del Registro – aggiungere in fondo
A4: Motivo | B4: Descrizione
A5: Prezzo troppo alto | B5: Il cliente ha scelto un concorrente più economico
A6: Zona fuori area / troppo lontana | B6: Trasferta non conveniente
A7: Servizio non offerto | B7: Richiesta per un servizio che non facciamo
A8: Cliente irreperibile | B8: Non risponde a telefono/mail dopo 2-3 tentativi
A9: Tempi non compatibili | B9: Il cliente voleva un intervento prima della nostra disponibilità
A10: Mezzo non adatto / accesso difficile | B10: Es. serve camion piccolo, strada non accessibile
A11: Problema già risolto | B11: Il cliente ha risolto da solo o con altri
A12: Solo informazioni / curiosità | B12: Nessuna intenzione reale di acquisto
A13: Mancanza documenti / requisiti | B13: Es. codice EER non autorizzato, manca analisi, oltre 50 t senza analisi
A14: Lavoro rifiutato da noi | B14: Non conveniente, rischio, cliente insolvente
A15: Richiesta duplicata | B15: Stesso cliente già a registro
A16: Altro (scrivere nelle note)

Sheet Liste
A1: PgCasa (Italiaonline) | B1: Privato | C1: SPURGHI E RETI | D1: PRESO | E1: SV
A2: Italiaonline | B2: Condominio / Amministratore | C2: RIFIUTI | D2: NON PRESO | E2: IM
A3: Internet | B3: Impresa edile / Artigiano | C3: BONIFICHE | D3: IN ATTESA | E3: GE
A4: Passaparola | B4: Azienda / Società | C4: DISINFESTAZIONE | D4: DA RICONTATTARE | E4: AL
A5: Pagine Gialle | B5: Attività / Turismo | C5: IGIENE IMPIANTI | D5: DA VERIFICARE | E5: AT
A6: Quotidiani Online | B6: Ente pubblico | C6: NAUTICA | E6: CN
A7: Pubblicità Automezzi | B7: Nautica / Porto | C7: CONSULENZA | E7: MI
A8: Manifesti deratt. | B8: Altro | C8: DA SPECIFICARE | E8: Altro
A9: Imprese Ambiente
A10: Bus
A11: Altro
